{
"skeleton": { "hash": "B51UuMx1oAh+/S+yBwcWEyUg9FY", "spine": "2.1.01", "width": 267.39, "height": 237.31, "images": "images" },
"bones": [
	{ "name": "root", "x": -7, "y": -135.32, "scaleX": 0.35, "scaleY": 0.35 },
	{ "name": "bone", "parent": "root", "length": 261.88, "x": -133.92, "y": 405.42, "rotation": 7.18 },
	{ "name": "bone26", "parent": "root", "length": 539.6, "x": 814.62, "y": -0.88, "rotation": 93.15 },
	{ "name": "bone28", "parent": "root", "length": 499.23, "x": -731.54, "y": 9.41, "rotation": 89.54 },
	{ "name": "bone29", "parent": "root", "length": 539.6, "x": 814.62, "y": -0.88, "rotation": 93.15 },
	{ "name": "bone12", "parent": "bone", "length": 136.09, "x": 9.91, "y": -111.46, "rotation": -148.11 },
	{ "name": "bone2", "parent": "bone", "length": 199.09, "x": 261.88, "y": 1.13, "rotation": -21.09 },
	{ "name": "bone22", "parent": "bone", "length": 96.91, "x": 5.61, "y": -19.88, "rotation": -161.56 },
	{ "name": "bone3", "parent": "bone", "length": 46.01, "x": 117.29, "y": -137.23, "rotation": -122.08 },
	{ "name": "bone8", "parent": "bone", "length": 249, "x": 182.13, "y": 35.34, "rotation": 119.4 },
	{ "name": "bone9", "parent": "bone", "length": 96.92, "x": -22.26, "y": -25.59, "rotation": 148.11 },
	{ "name": "bone10", "parent": "bone9", "length": 76.7, "x": 96.92, "y": -0.26, "rotation": 8.06 },
	{ "name": "bone13", "parent": "bone12", "length": 28.76, "x": 127.73, "y": -33.94, "rotation": -61.13 },
	{ "name": "bone14", "parent": "bone12", "length": 52.8, "x": 132.71, "y": 23.71, "rotation": 59.64 },
	{ "name": "bone15", "parent": "bone2", "length": 72.46, "x": 42.13, "y": 17.23, "rotation": 157.34 },
	{ "name": "bone17", "parent": "bone2", "length": 85.13, "x": 14.74, "y": 123.56, "rotation": 134.77 },
	{ "name": "bone18", "parent": "bone2", "length": 43.06, "x": 55.42, "y": -65.97, "rotation": -150.79 },
	{ "name": "bone19", "parent": "bone2", "length": 56.19, "x": 98.66, "y": -93.77, "rotation": -88.18 },
	{ "name": "bone21", "parent": "bone2", "length": 49.64, "x": 116.24, "y": -85.46, "rotation": -50.73 },
	{ "name": "bone23", "parent": "bone22", "length": 30.83, "x": 83.27, "y": -12.72, "rotation": -64.16 },
	{ "name": "bone24", "parent": "bone22", "length": 40.93, "x": 85.43, "y": 15.62, "rotation": 63.97 },
	{ "name": "bone4", "parent": "bone3", "length": 168.79, "x": 46.01, "rotation": 24.54 },
	{ "name": "bone11", "parent": "bone10", "length": 76.35, "x": 76.7, "y": 0.54, "rotation": 9.38 },
	{ "name": "bone16", "parent": "bone15", "length": 58.87, "x": 73.61, "y": -0.61, "rotation": -22.65 },
	{ "name": "bone20", "parent": "bone19", "length": 45.92, "x": 56.18, "y": 0.34, "rotation": -22.26 },
	{ "name": "bone5", "parent": "bone4", "length": 89.09, "x": 118.14, "y": -11.09, "rotation": -69.29 },
	{ "name": "bone7", "parent": "bone4", "length": 71.28, "x": 25.18, "y": -45.05, "rotation": -71.95 },
	{ "name": "bone6", "parent": "bone5", "length": 75.53, "x": 90.64, "y": -0.65, "rotation": 15.37 }
],
"slots": [
	{ "name": "chibang22", "bone": "bone8", "attachment": "chibang2" },
	{ "name": "yumao12", "bone": "bone17", "attachment": "yumao1" },
	{ "name": "daizi22", "bone": "bone21", "attachment": "daizi2" },
	{ "name": "daizi12", "bone": "bone19", "attachment": "daizi1" },
	{ "name": "jiao22", "bone": "bone22", "attachment": "jiao2" },
	{ "name": "jiao12", "bone": "bone12", "attachment": "jiao1" },
	{ "name": "weiba2", "bone": "bone9", "attachment": "weiba" },
	{ "name": "shenti2", "bone": "bone", "attachment": "shenti" },
	{ "name": "yumao2", "bone": "bone18", "attachment": "yumao2" },
	{ "name": "yumao32", "bone": "bone15", "attachment": "yumao3" },
	{ "name": "chibang12", "bone": "bone3", "attachment": "chibang1" },
	{ "name": "gongji/qiangkou/qiangkou018", "bone": "bone26" },
	{ "name": "gongji/qiangkou/qiangkou0182", "bone": "bone29" },
	{ "name": "jineng/zhuaji019", "bone": "bone28" }
],
"skins": {
	"default": {
		"chibang12": {
			"chibang1": {
				"type": "skinnedmesh",
				"uvs": [ 1, 0.21238, 0.90485, 0.26533, 0.91942, 0.38225, 0.9343, 0.50169, 0.86182, 0.69112, 0.65145, 0.78583, 0.36684, 0.83004, 0.19536, 0.90897, 0.09637, 1, 0.04637, 0.99285, 0.00159, 0.87153, 0, 0.66586, 0.06455, 0.43065, 0.27491, 0.1323, 0.42985, 0.0912, 0.49891, 0, 1, 0, 0.76652, 0.19687, 0.56974, 0.12792, 0.3138, 0.65797, 0.28729, 0.50169, 0.26431, 0.31226, 0.12542, 0.76147, 0.09288, 0.58464, 0.62654, 0.58619, 0.56614, 0.23689, 0.59923, 0.4301 ],
				"triangles": [ 7, 8, 10, 8, 9, 10, 10, 22, 7, 7, 22, 6, 10, 11, 22, 22, 19, 6, 11, 23, 22, 22, 23, 19, 11, 12, 23, 23, 20, 19, 23, 12, 20, 5, 6, 24, 6, 19, 24, 19, 20, 24, 20, 26, 24, 12, 21, 20, 20, 21, 26, 21, 12, 13, 21, 25, 26, 21, 14, 25, 21, 13, 14, 5, 24, 4, 4, 24, 3, 24, 26, 3, 26, 2, 3, 25, 14, 18, 14, 15, 18, 25, 18, 17, 1, 17, 0, 17, 16, 0, 16, 17, 15, 17, 18, 15, 2, 17, 1, 26, 25, 17, 2, 26, 17 ],
				"vertices": [ 1, 8, 22.74, 83.58, 1, 1, 8, 47.79, 67.2, 1, 5, 8, 77.87, 85.44, 0.4, 21, 64.46, 64.48, 0.59999, 26, -91.98, 71.27, 0, 25, -89.67, -23.49, 0, 27, -179.92, 25.8, 0, 4, 8, 108.59, 104.07, 1.2E-4, 21, 100.15, 68.67, 0.99985, 25, -80.97, 11.36, 1.0E-5, 27, -162.28, 57.1, 0, 4, 8, 168.11, 110.35, 0, 21, 156.9, 49.65, 0.99984, 25, -43.12, 57.73, 1.4E-4, 27, -113.49, 91.77, 0, 3, 21, 185.56, -6.33, 0.91736, 25, 19.38, 64.74, 0.07821, 27, -51.36, 81.95, 0.00441, 3, 21, 199.22, -82.25, 0.00868, 25, 95.22, 50.7, 0.27989, 27, 18.03, 48.3, 0.71142, 2, 25, 146.36, 56.9, 2.4E-4, 27, 68.98, 40.71, 0.99975, 1, 27, 106.33, 47.36, 1, 1, 27, 115.92, 37.83, 1, 1, 27, 104.43, 1.4, 1, 3, 8, 258.09, -101.56, 0, 26, 167.65, 77.42, 0.06713, 27, 68.86, -48.75, 0.93286, 4, 8, 187.04, -115.52, 0, 26, 129.85, 15.66, 0.57694, 25, 129.35, -89.33, 0.0356, 27, 13.79, -95.77, 0.38744, 3, 8, 82.48, -102.11, 0.4, 26, 49.22, -52.24, 0.6, 27, -83.89, -135.37, 0, 1, 8, 53.92, -69.75, 1, 1, 8, 21.43, -64.5, 1, 1, 8, -34.86, 56.86, 1, 1, 8, 44.76, 25.08, 1, 1, 8, 48.17, -31.25, 1, 4, 8, 220.69, -26.55, 0, 26, 87.11, 100.65, 0.00509, 25, 90.6, -2.45, 0.45367, 27, -0.52, -1.73, 0.54123, 4, 8, 181.28, -52.63, 0, 26, 79.65, 53.98, 0.36187, 25, 80.98, -48.73, 0.42663, 27, -22.06, -43.79, 0.21148, 1, 26, 68.28, -1.84, 1, 4, 8, 269.93, -59.16, 0, 26, 144.44, 114.84, 0.00347, 25, 148.52, 9.05, 0, 27, 58.38, -5.98, 0.99652, 4, 8, 225.62, -89.29, 0, 26, 136.64, 61.83, 0.19823, 25, 138.27, -43.53, 0.02234, 27, 34.55, -53.98, 0.77942, 3, 8, 166.09, 40.16, 0, 21, 125.9, -13.34, 0.15356, 25, 4.85, 6.46, 0.84643, 5, 8, 78.13, -18.41, 0.4, 21, 21.56, -30.09, 0.19548, 26, -15.34, 1.19, 0.40341, 25, -16.36, -97.05, 0.00109, 27, -128.74, -64.57, 0, 5, 8, 126.82, 13.9, 0, 21, 79.28, -20.91, 0.51359, 26, -6.19, 58.91, 0.13519, 25, -4.54, -39.82, 0.35121, 27, -102.17, -12.52, 0 ],
				"hull": 17,
				"edges": [ 2, 34, 34, 36, 36, 28, 30, 32, 28, 30, 0, 32, 2, 0, 6, 8, 8, 10, 10, 12, 12, 14, 16, 18, 14, 16, 12, 38, 38, 40, 40, 42, 42, 26, 26, 28, 26, 24, 24, 22, 14, 44, 24, 46, 46, 44, 38, 44, 18, 20, 20, 22, 44, 20, 38, 48, 48, 10, 48, 6, 50, 36, 50, 42, 42, 24, 50, 34, 48, 52, 52, 50, 40, 52, 2, 4, 4, 6, 52, 4 ],
				"width": 267,
				"height": 299
			}
		},
		"chibang22": {
			"chibang2": { "x": 98.76, "y": -10.99, "rotation": -126.58, "width": 215, "height": 243 }
		},
		"daizi12": {
			"daizi1": {
				"type": "skinnedmesh",
				"uvs": [ 1, 0.16197, 0.98236, 0.40328, 0.9126, 0.64081, 0.73371, 0.84897, 0.57598, 1, 0.39582, 1, 0.21372, 0.95679, 0, 0.90608, 0, 0.80395, 0.1858, 0.69689, 0.37592, 0.54103, 0.49685, 0.34165, 0.54874, 0.13617, 0.58268, 0, 0.79772, 0, 1, 0, 0.44117, 0.76777, 0.61514, 0.58551, 0.71502, 0.36611, 0.76433, 0.15002 ],
				"triangles": [ 19, 13, 14, 14, 15, 0, 12, 13, 19, 19, 14, 0, 16, 10, 17, 9, 10, 16, 3, 17, 2, 16, 17, 3, 6, 7, 8, 6, 9, 16, 6, 8, 9, 5, 6, 16, 4, 5, 16, 3, 4, 16, 18, 12, 19, 11, 12, 18, 1, 19, 0, 18, 19, 1, 17, 11, 18, 10, 11, 17, 2, 18, 1, 17, 18, 2 ],
				"vertices": [ 2, 17, 4.8, 19.25, 0.53999, 6, 118.05, -97.96, 0.46, 3, 17, 31.03, 23.55, 0.799, 24, -32.07, 11.94, 0.141, 6, 123.19, -124.04, 0.06, 2, 17, 57.64, 24.05, 0.59333, 24, -7.63, 22.49, 0.40666, 2, 17, 82.77, 16.08, 0.12, 24, 18.63, 24.64, 0.88, 1, 24, 38.84, 24.52, 1, 1, 24, 46.27, 13.66, 1, 1, 24, 49.85, 0.01, 1, 1, 24, 54.06, -16.01, 1, 1, 24, 44.78, -22.35, 1, 2, 17, 74.79, -26.53, 0.12, 24, 27.41, -17.81, 0.88, 2, 17, 55.12, -16.55, 0.38136, 24, 5.42, -16.03, 0.61863, 3, 17, 31.83, -12.51, 0.799, 24, -17.66, -21.13, 0.141, 6, 87.16, -125.99, 0.06, 2, 17, 8.93, -13.55, 0.53999, 6, 85.4, -103.14, 0.46, 1, 6, 84.2, -88, 1, 1, 6, 99.43, -84.22, 1, 1, 6, 113.77, -80.67, 1, 2, 17, 78.51, -6.67, 0.12, 24, 23.32, 1.97, 0.88, 2, 17, 56.24, 1.54, 0.52301, 24, -0.39, 1.13, 0.47698, 3, 17, 31.12, 3.61, 0.799, 24, -24.43, -6.47, 0.141, 6, 103.26, -124.77, 0.06, 2, 17, 7.12, 2.15, 0.53999, 6, 101.04, -100.83, 0.46 ],
				"hull": 16,
				"edges": [ 20, 22, 2, 4, 4, 6, 18, 20, 6, 8, 18, 16, 14, 16, 8, 10, 10, 12, 12, 14, 6, 32, 32, 18, 12, 32, 4, 34, 34, 20, 32, 34, 2, 36, 36, 22, 34, 36, 26, 28, 28, 30, 2, 0, 0, 30, 28, 38, 38, 36, 0, 38, 22, 24, 24, 26, 38, 24 ],
				"width": 73,
				"height": 110
			}
		},
		"daizi22": {
			"daizi2": {
				"type": "skinnedmesh",
				"uvs": [ 0.55653, 0.13329, 0.7529, 0.38766, 1, 0.76399, 1, 1, 0.75535, 1, 0.36792, 1, 0.27761, 0.6176, 0.14801, 0.3702, 0.0734, 0.1472, 0.18403, 0.08139, 0.32087, 0, 0.39157, 0, 0.35368, 0.25093, 0.51321, 0.50362 ],
				"triangles": [ 7, 8, 9, 9, 10, 12, 12, 10, 11, 7, 9, 12, 12, 11, 0, 4, 2, 3, 5, 13, 4, 4, 13, 2, 2, 13, 1, 5, 6, 13, 6, 12, 13, 6, 7, 12, 13, 0, 1, 13, 12, 0 ],
				"vertices": [ 2, 18, 0.81, 13.31, 0.49, 6, 127.07, -77.67, 0.51, 2, 18, 19.68, 16.32, 0.84, 6, 141.34, -90.38, 0.16, 1, 18, 46.59, 18.61, 1, 1, 18, 59.81, 12.35, 1, 1, 18, 54.05, 0.19, 1, 1, 18, 44.93, -19.06, 1, 2, 18, 21.38, -13.4, 0.84, 6, 119.39, -110.5, 0.16, 2, 18, 4.46, -13.28, 0.49, 6, 108.79, -97.32, 0.51, 1, 6, 101.48, -84.89, 1, 1, 6, 106.41, -79.47, 1, 1, 6, 112.5, -72.76, 1, 1, 6, 116.27, -71.83, 1, 2, 18, 2.62, 0.1, 0.49, 6, 117.99, -87.43, 0.51, 2, 18, 20.54, 1.33, 0.84, 6, 130.27, -100.53, 0.16 ],
				"hull": 12,
				"edges": [ 14, 16, 20, 22, 0, 22, 0, 2, 12, 14, 6, 4, 2, 4, 12, 10, 16, 18, 18, 20, 0, 24, 24, 14, 18, 24, 2, 26, 26, 12, 24, 26, 6, 8, 8, 10, 26, 8 ],
				"width": 55,
				"height": 62
			}
		},
		"gongji/qiangkou/qiangkou018": {
			"gongji/qiangkou/qiangkou018": { "x": 238.59, "y": -15.56, "rotation": -93.15, "width": 150, "height": 150 },
			"gongji/qiangkou/qiangkou019": { "x": 238.59, "y": -15.56, "rotation": -93.15, "width": 150, "height": 150 },
			"gongji/qiangkou/qiangkou020": { "x": 238.59, "y": -15.56, "rotation": -93.15, "width": 150, "height": 150 },
			"gongji/qiangkou/qiangkou021": { "x": 238.59, "y": -15.56, "rotation": -93.15, "width": 150, "height": 150 }
		},
		"gongji/qiangkou/qiangkou0182": {
			"gongji/qiangkou/qiangkou018": { "x": 238.59, "y": -15.56, "rotation": -93.15, "width": 150, "height": 150 },
			"gongji/qiangkou/qiangkou019": { "x": 238.59, "y": -15.56, "rotation": -93.15, "width": 150, "height": 150 },
			"gongji/qiangkou/qiangkou020": { "x": 238.59, "y": -15.56, "rotation": -93.15, "width": 150, "height": 150 },
			"gongji/qiangkou/qiangkou021": { "x": 238.59, "y": -15.56, "rotation": -93.15, "width": 150, "height": 150 }
		},
		"jiao12": {
			"jiao1": {
				"type": "skinnedmesh",
				"uvs": [ 1, 0.36534, 0.54618, 0.50577, 0.4316, 0.63985, 0.46047, 0.72438, 0.47093, 0.84472, 0.41607, 1, 0.30208, 1, 0.24126, 1, 0.16182, 0.9554, 0.26038, 0.87661, 0.22533, 0.77844, 0.20172, 0.68863, 0.14925, 0.55726, 0.11459, 0.48074, 0.07028, 0.45094, 0, 0.54752, 0, 0.43397, 0, 0.32207, 0.08782, 0.25461, 0.20192, 0.3379, 0.28135, 0.37393, 0.43599, 0.23587, 0.55456, 0, 1, 0, 0.31757, 0.66405, 0.34607, 0.75068, 0.35998, 0.86152, 0.22183, 0.45654, 0.16175, 0.4036, 0.07846, 0.35942 ],
				"triangles": [ 25, 3, 4, 26, 25, 4, 9, 10, 25, 26, 9, 25, 7, 8, 9, 6, 9, 26, 7, 9, 6, 5, 26, 4, 6, 26, 5, 29, 17, 18, 29, 18, 19, 28, 29, 19, 16, 17, 29, 14, 16, 29, 14, 29, 28, 13, 14, 28, 15, 16, 14, 25, 2, 3, 10, 24, 25, 12, 13, 27, 22, 23, 0, 21, 22, 0, 1, 21, 0, 20, 21, 1, 27, 20, 2, 24, 12, 27, 2, 20, 1, 2, 24, 27, 11, 12, 24, 27, 19, 20, 25, 24, 2, 10, 11, 24, 28, 19, 27, 13, 28, 27 ],
				"vertices": [ 1, 5, 3.64, 58.42, 1, 1, 5, 85.11, 25.58, 1, 1, 5, 117.12, 31.39, 1, 2, 5, 122.77, 46.83, 0.46, 13, 14.92, 20.26, 0.53999, 2, 5, 135.22, 65.24, 0.12, 13, 37.1, 18.83, 0.88, 1, 13, 63.81, 4.48, 1, 1, 13, 60.63, -16.36, 1, 1, 13, 58.93, -27.48, 1, 1, 13, 48.59, -40.77, 1, 2, 5, 169.16, 45.25, 0.12, 13, 37.02, -20.56, 0.88, 2, 5, 162.82, 27.14, 0.46, 13, 18.18, -24.24, 0.53999, 1, 5, 155.8, 11.56, 1, 1, 5, 148.1, -13.32, 1, 2, 5, 144.21, -28.29, 0.52, 12, 3.01, 17.16, 0.48, 2, 5, 147.12, -37.71, 0.14, 12, 12.67, 15.15, 0.86, 2, 5, 168.42, -32.11, 0, 12, 18.04, 36.51, 0.99999, 1, 12, 25.89, 17.15, 1, 1, 12, 33.63, -1.92, 1, 2, 5, 121.84, -63.72, 0.14, 12, 23.23, -19.53, 0.86, 2, 5, 115.11, -38.52, 0.52, 12, -2.08, -13.26, 0.48, 1, 5, 107.87, -24.11, 1, 1, 5, 69.65, -25.81, 1, 1, 5, 25.27, -45.7, 1, 1, 5, -38.71, 6.22, 1, 1, 5, 136.3, 21.55, 1, 2, 5, 142.26, 37.25, 0.46, 13, 16.51, -1.38, 0.53999, 2, 5, 153.11, 54.71, 0.12, 13, 37.06, -1.92, 0.88, 1, 5, 126, -19.25, 1, 2, 5, 128.49, -33.81, 0.52, 12, 0.26, 0.72, 0.48, 2, 5, 135.34, -49.84, 0.14, 12, 17.59, -1.01, 0.86 ],
				"hull": 24,
				"edges": [ 4, 6, 20, 22, 6, 8, 20, 18, 18, 16, 16, 14, 8, 10, 24, 26, 40, 38, 38, 36, 36, 34, 40, 42, 44, 46, 42, 44, 4, 2, 0, 46, 2, 0, 22, 24, 28, 26, 28, 30, 4, 48, 48, 22, 6, 50, 50, 20, 48, 50, 8, 52, 52, 18, 50, 52, 10, 12, 12, 14, 52, 12, 24, 54, 54, 40, 26, 56, 56, 38, 54, 56, 28, 58, 58, 36, 56, 58, 30, 32, 32, 34, 58, 32 ],
				"width": 185,
				"height": 184
			}
		},
		"jiao22": {
			"jiao2": {
				"type": "skinnedmesh",
				"uvs": [ 1, 0.47589, 0.68528, 0.49546, 0.40329, 0.59386, 0.4045, 0.71317, 0.39969, 0.85618, 0.30456, 1, 0.1855, 1, 0.03835, 1, 0.15406, 0.89353, 0.15094, 0.77436, 0.15112, 0.66271, 0.1184, 0.47122, 0.08144, 0.37658, 0, 0.44847, 0, 0.29327, 0.09914, 0.16273, 0.19951, 0.24415, 0.27523, 0.32367, 0.44839, 0.23549, 0.60564, 0, 1, 0, 0.21439, 0.38091, 0.13746, 0.31376, 0.28678, 0.62567, 0.28086, 0.74301, 0.27259, 0.88086 ],
				"triangles": [ 13, 14, 12, 12, 14, 22, 16, 22, 15, 22, 14, 15, 6, 25, 5, 5, 25, 4, 7, 8, 6, 6, 8, 25, 8, 9, 25, 25, 24, 4, 25, 9, 24, 4, 24, 3, 21, 11, 12, 17, 21, 16, 23, 11, 21, 21, 17, 2, 9, 10, 24, 24, 23, 3, 24, 10, 23, 23, 2, 3, 2, 23, 21, 2, 18, 1, 2, 17, 18, 20, 0, 1, 1, 18, 19, 1, 19, 20, 10, 11, 23, 21, 12, 22, 21, 22, 16 ],
				"vertices": [ 1, 7, -5.19, 41.69, 1, 2, 7, 32.72, 26.14, 0.99717, 20, -13.66, 51.97, 0.00282, 1, 7, 70.92, 21.03, 1, 2, 7, 77.02, 34.12, 0.47, 20, 12.93, 15.66, 0.52999, 2, 7, 85.06, 49.45, 0.09, 20, 30.24, 15.16, 0.91, 2, 7, 103.74, 59.8, 0, 20, 47.73, 2.92, 1, 2, 7, 117.69, 53.11, 0, 20, 47.84, -12.55, 1, 2, 7, 134.95, 44.84, 0, 20, 47.97, -31.68, 1, 2, 7, 115.81, 39.72, 0.09, 20, 34.98, -16.73, 0.91, 2, 7, 109.95, 26.54, 0.47, 20, 20.57, -17.24, 0.52999, 1, 7, 104.09, 14.37, 1, 1, 7, 97.91, -8.35, 1, 3, 7, 97.29, -20.75, 0.48, 20, -27.49, -26.61, 8.0E-5, 19, 13.34, 9.11, 0.51991, 2, 20, -18.71, -37.14, 4.0E-5, 19, 16.2, 22.51, 0.99995, 3, 7, 102.48, -34.42, 0, 20, -37.49, -37.27, 0, 19, 27.9, 7.82, 0.99999, 3, 7, 84.03, -43.09, 0.26, 20, -53.38, -24.5, 0, 19, 27.67, -12.55, 0.73999, 2, 7, 76.52, -28.57, 0.48, 19, 11.32, -12.98, 0.52, 1, 7, 71.8, -15.64, 1, 2, 7, 46.89, -15.53, 0.99464, 19, -13.32, -33.96, 0.00535, 1, 7, 16.14, -32.39, 1, 1, 7, -30.08, -10.23, 1, 1, 7, 81.93, -12.81, 1, 2, 7, 87.44, -24.46, 0.48, 19, 12.38, -1.37, 0.52, 1, 7, 86.24, 17.95, 1, 2, 7, 93.08, 30.42, 0.47, 20, 16.65, -0.38, 0.52999, 2, 7, 101.25, 45, 0.09, 20, 33.34, -1.33, 0.91 ],
				"hull": 21,
				"edges": [ 0, 40, 0, 2, 2, 4, 18, 20, 4, 6, 6, 8, 8, 10, 18, 16, 16, 14, 22, 24, 32, 34, 32, 30, 30, 28, 26, 28, 24, 26, 34, 42, 42, 22, 24, 44, 44, 32, 42, 44, 44, 28, 4, 46, 46, 20, 6, 48, 48, 18, 46, 48, 48, 50, 50, 8, 50, 16, 10, 12, 12, 14, 50, 12, 34, 36, 38, 40, 36, 38, 22, 20 ],
				"width": 130,
				"height": 121
			}
		},
		"jineng/zhuaji019": {
			"jineng/zhuaji019": { "x": 249.1, "y": 63.13, "rotation": -89.54, "width": 590, "height": 310 },
			"jineng/zhuaji020": { "x": 249.1, "y": 63.13, "rotation": -89.54, "width": 590, "height": 310 },
			"jineng/zhuaji021": { "x": 249.1, "y": 63.13, "rotation": -89.54, "width": 590, "height": 310 },
			"jineng/zhuaji022": { "x": 249.1, "y": 63.13, "rotation": -89.54, "width": 590, "height": 310 },
			"jineng/zhuaji023": { "x": 249.1, "y": 63.13, "rotation": -89.54, "width": 590, "height": 310 },
			"jineng/zhuaji024": { "x": 249.1, "y": 63.13, "rotation": -89.54, "width": 590, "height": 310 }
		},
		"shenti2": {
			"shenti": {
				"type": "skinnedmesh",
				"uvs": [ 0.5847, 0.15871, 0.63727, 0.13678, 0.69539, 0.07632, 0.79425, 0.09202, 0.92767, 0.19749, 1, 0.37077, 1, 0.44888, 0.83767, 0.46919, 0.75133, 0.495, 0.69719, 0.49264, 0.64328, 0.50833, 0.62239, 0.63305, 0.49291, 0.67758, 0.25231, 0.59643, 0.15345, 0.44165, 0.18396, 0.23641, 0.22682, 0.05959, 0.38567, 0, 0.55211, 0, 0.81924, 0.30916, 0.72678, 0.31125, 0.59842, 0.3263, 0.66651, 0.31832 ],
				"triangles": [ 9, 22, 20, 22, 1, 20, 7, 8, 20, 8, 9, 20, 20, 19, 7, 6, 7, 5, 7, 19, 5, 19, 4, 5, 3, 20, 2, 20, 3, 19, 2, 20, 1, 19, 3, 4, 10, 22, 9, 0, 1, 22, 11, 12, 10, 10, 12, 13, 10, 13, 21, 13, 14, 21, 10, 21, 22, 21, 15, 0, 18, 0, 17, 17, 0, 15, 17, 15, 16, 21, 14, 15, 21, 0, 22 ],
				"vertices": [ 1, 1, 235.84, 89.78, 1, 1, 6, -25, 94.85, 1, 1, 6, 4.16, 140.02, 1, 1, 6, 71.13, 146.76, 1, 1, 6, 173.87, 106.06, 1, 1, 6, 246.58, 15.35, 1, 1, 6, 258.02, -30.82, 1, 1, 6, 154.8, -69.14, 1, 1, 6, 102.09, -98.4, 1, 1, 6, 66.33, -105.79, 1, 1, 1, 248.5, -126.37, 1, 1, 1, 225.07, -199.98, 1, 1, 1, 135.11, -216.02, 1, 1, 1, -19.62, -146.8, 1, 1, 1, -73.99, -44.98, 1, 2, 1, -38.03, 76.46, 0.99999, 6, -306.98, -37.54, 0, 2, 1, 4.02, 179.71, 1, 6, -304.84, 73.92, 0, 1, 1, 114.77, 202.39, 1, 1, 1, 226.07, 188.42, 1, 1, 6, 119.3, 22.46, 1, 1, 6, 59.11, 6.23, 1, 1, 1, 232.3, -12.62, 1, 1, 6, 20.71, -7.71, 1 ],
				"hull": 19,
				"edges": [ 16, 14, 14, 12, 12, 10, 10, 8, 8, 6, 6, 4, 20, 22, 22, 24, 24, 26, 26, 28, 28, 30, 30, 32, 32, 34, 34, 36, 0, 36, 6, 38, 38, 14, 10, 38, 4, 40, 40, 16, 38, 40, 0, 42, 42, 20, 42, 28, 16, 18, 18, 20, 40, 44, 44, 42, 18, 44, 0, 2, 2, 4, 44, 2 ],
				"width": 674,
				"height": 609
			}
		},
		"weiba2": {
			"weiba": {
				"type": "skinnedmesh",
				"uvs": [ 0.47195, 0.09054, 0.63253, 0.18321, 0.80514, 0.35889, 1, 0.60041, 1, 0.73477, 0.92625, 0.89301, 0.81073, 0.90604, 0.61016, 1, 0.47746, 0.99999, 0.32139, 0.99998, 0.17813, 0.99999, 0.1194, 0.99999, 0, 0.80349, 0, 0.25252, 0.1309, 3.0E-5, 0.31519, 7.0E-5, 0.80707, 0.54784, 0.6254, 0.44337, 0.47373, 0.38358, 0.31727, 0.33633, 0.14555, 0.3101, 0.80896, 0.73289, 0.61697, 0.75123, 0.47601, 0.76133, 0.31991, 0.76135, 0.16723, 0.76918 ],
				"triangles": [ 10, 11, 25, 11, 12, 25, 9, 10, 24, 10, 25, 24, 12, 20, 25, 12, 13, 20, 25, 19, 24, 25, 20, 19, 0, 19, 15, 13, 14, 20, 19, 20, 15, 20, 14, 15, 9, 24, 23, 24, 18, 23, 24, 19, 18, 17, 23, 18, 2, 17, 1, 19, 0, 18, 17, 18, 1, 18, 0, 1, 6, 7, 22, 9, 23, 8, 22, 7, 23, 7, 8, 23, 22, 21, 6, 6, 21, 5, 5, 21, 4, 22, 23, 17, 22, 16, 21, 22, 17, 16, 4, 16, 3, 4, 21, 16, 17, 2, 16, 3, 16, 2 ],
				"vertices": [ 3, 10, 174.91, -80.32, 0.00663, 11, 65.98, -90.21, 0.58944, 22, -25.4, -87.78, 0.40391, 3, 10, 129.2, -76.27, 0.10047, 11, 21.29, -79.79, 0.79854, 22, -67.78, -70.2, 0.10097, 2, 10, 72.24, -54.93, 0.71645, 11, -32.1, -50.66, 0.28354, 2, 10, 3.49, -21.18, 1.00001, 11, -95.44, -7.6, -1.0E-5, 1, 10, -10.32, 8.83, 1, 2, 10, -10, 51.84, 0.99758, 11, -98.56, 66.59, 0.00241, 3, 10, 14.67, 66.74, 0.96057, 11, -72.03, 77.87, 0.03685, 22, -134.1, 100.6, 0.00256, 3, 10, 50.18, 108.54, 0.71691, 11, -31.01, 114.28, 0.22795, 22, -87.68, 129.81, 0.05513, 3, 10, 80.08, 122.3, 0.51943, 11, 0.51, 123.72, 0.33698, 22, -55.03, 133.97, 0.14357, 3, 10, 115.23, 138.49, 0.27788, 11, 37.59, 134.82, 0.38556, 22, -16.64, 138.86, 0.33655, 3, 10, 147.5, 153.36, 0.14153, 11, 71.62, 145.01, 0.34043, 22, 18.59, 143.35, 0.51802, 3, 10, 160.73, 159.45, 0.11988, 11, 85.58, 149.19, 0.3253, 22, 33.04, 145.19, 0.55481, 3, 10, 207.85, 127.93, 0.04098, 11, 127.81, 111.37, 0.20949, 22, 68.53, 100.99, 0.74952, 3, 10, 264.55, 4.83, 0, 11, 166.68, -18.46, 0.00699, 22, 85.66, -33.45, 0.99299, 3, 10, 261.05, -65.16, 3.0E-5, 11, 153.39, -87.28, 0.14631, 22, 61.31, -99.17, 0.85364, 3, 10, 219.53, -84.27, 0, 11, 109.61, -100.38, 0.29474, 22, 15.97, -104.94, 0.70525, 2, 10, 52.36, -12.91, 0.99365, 11, -45.89, -6.27, 0.00634, 3, 10, 104.03, -17.41, 0.31229, 11, 4.63, -17.97, 0.68716, 22, -74.12, -6.49, 5.3E-4, 3, 10, 144.35, -15.03, 0.00366, 11, 44.88, -21.27, 0.95667, 22, -34.95, -16.32, 0.03965, 2, 11, 85.39, -21.28, 0.36116, 22, 5, -22.95, 0.63883, 3, 10, 225.84, 2.59, 0, 11, 128.04, -15.25, 0.01706, 22, 48.06, -23.97, 0.98293, 3, 10, 32.89, 28.23, 0.99163, 11, -59.4, 37.19, 0.00829, 22, -128.28, 58.4, 7.0E-5, 3, 10, 74.25, 52.25, 0.7475, 11, -15.08, 55.17, 0.23261, 22, -81.62, 68.89, 0.01987, 3, 10, 104.96, 69.13, 0.40997, 11, 17.69, 67.58, 0.48094, 22, -47.26, 75.77, 0.10907, 3, 10, 140.12, 85.33, 0.17081, 11, 54.78, 78.68, 0.46954, 22, -8.85, 80.67, 0.35964, 3, 10, 173.71, 102.92, 0.07004, 11, 90.5, 91.39, 0.28585, 22, 28.45, 87.37, 0.64409 ],
				"hull": 16,
				"edges": [ 28, 30, 28, 26, 24, 26, 22, 24, 4, 2, 12, 14, 10, 12, 10, 8, 8, 6, 6, 4, 14, 16, 16, 18, 2, 0, 0, 30, 18, 20, 20, 22, 4, 32, 8, 32, 2, 34, 32, 34, 0, 36, 34, 36, 38, 30, 36, 38, 40, 28, 38, 40, 40, 26, 12, 42, 42, 32, 8, 42, 14, 44, 44, 34, 42, 44, 16, 46, 46, 36, 44, 46, 18, 48, 48, 38, 46, 48, 20, 50, 50, 40, 48, 50, 50, 24, 32, 6 ],
				"width": 248,
				"height": 246
			}
		},
		"yumao12": {
			"yumao1": {
				"type": "skinnedmesh",
				"uvs": [ 0.39543, 0.30091, 0.60993, 0.47309, 0.8276, 0.59345, 1, 0.68877, 1, 1, 0.60294, 1, 0.22093, 0.83762, 0.27801, 0.66564, 0.09389, 0.46126, 0, 0.23971, 0, 0, 0.10532, 0, 0.57164, 0.69646, 0.45179, 0.56483, 0.23292, 0.38733 ],
				"triangles": [ 8, 14, 7, 7, 14, 13, 14, 0, 13, 13, 0, 1, 8, 9, 14, 0, 14, 11, 11, 14, 10, 14, 9, 10, 12, 7, 13, 12, 13, 1, 12, 6, 7, 12, 1, 2, 4, 2, 3, 6, 12, 5, 2, 4, 12, 4, 5, 12 ],
				"vertices": [ 2, 6, 1.55, 156.29, 0.16, 15, 32.52, -13.67, 0.84, 2, 6, 26.01, 138.75, 0.48, 15, 2.85, -18.69, 0.52, 1, 6, 49.09, 127.98, 1, 1, 6, 67.37, 119.45, 1, 1, 6, 77.33, 79.27, 1, 1, 6, 42.25, 70.57, 1, 1, 6, 3.31, 83.17, 1, 2, 6, 2.85, 106.63, 0.48, 15, -3.65, 20.36, 0.52, 2, 6, -19.94, 128.98, 0.16, 15, 28.27, 20.81, 0.84, 1, 15, 57.95, 13.04, 1, 1, 15, 85.33, -3.29, 1, 1, 15, 80.41, -11.52, 1, 1, 6, 29.78, 109.08, 1, 2, 6, 14.98, 123.45, 0.48, 15, -0.24, -0.08, 0.52, 2, 6, -10.03, 141.57, 0.16, 15, 30.23, 4.91, 0.84 ],
				"hull": 12,
				"edges": [ 8, 6, 14, 12, 8, 10, 12, 10, 2, 0, 16, 14, 18, 20, 16, 18, 20, 22, 0, 22, 2, 4, 4, 6, 4, 24, 24, 12, 8, 24, 2, 26, 26, 14, 24, 26, 0, 28, 28, 16, 26, 28, 28, 20 ],
				"width": 91,
				"height": 133
			}
		},
		"yumao2": {
			"yumao2": {
				"type": "skinnedmesh",
				"uvs": [ 0.73652, 0.38407, 1, 0.76341, 0.73625, 0.87469, 0.51379, 1, 0.41001, 1, 0.44477, 0.68671, 0, 0.62743, 0.16322, 0.42219, 0.34616, 0.2587, 0, 0.10204, 0.33148, 0, 0.59836, 0, 0.60294, 0.63804, 0.44993, 0.30048 ],
				"triangles": [ 13, 8, 10, 9, 10, 8, 13, 7, 8, 5, 13, 12, 5, 7, 13, 6, 7, 5, 5, 12, 2, 3, 5, 2, 4, 5, 3, 11, 13, 10, 12, 13, 0, 2, 12, 1, 13, 11, 0, 12, 0, 1 ],
				"vertices": [ 1, 6, 52.93, -60.33, 1, 1, 6, 79.53, -92.04, 1, 2, 6, 64.48, -107.01, 0.38, 16, 12.1, 40.23, 0.62, 1, 16, 30.14, 48.03, 1, 1, 16, 37.05, 46.15, 1, 2, 6, 40.53, -93.97, 0.26, 16, 26.65, 17.16, 0.74, 1, 16, 54.72, 3.47, 1, 1, 16, 38.55, -12.95, 1, 2, 6, 23.83, -54.89, 0.26, 16, 22.15, -25.08, 0.74, 1, 16, 41.15, -46.19, 1, 2, 6, 16.75, -30.52, 0.38, 16, 16.45, -49.81, 0.62, 1, 6, 34.62, -26.09, 1, 2, 6, 49.98, -86.71, 0.38, 16, 14.86, 15.44, 0.62, 2, 6, 31.77, -57.14, 0.38, 16, 16.33, -19.25, 0.62 ],
				"hull": 12,
				"edges": [ 2, 0, 0, 22, 2, 4, 4, 24, 24, 26, 20, 22, 26, 20, 4, 6, 20, 18, 6, 8, 8, 10, 10, 12, 12, 14, 14, 16, 16, 18 ],
				"width": 69,
				"height": 98
			}
		},
		"yumao32": {
			"yumao3": {
				"type": "skinnedmesh",
				"uvs": [ 0.35612, 0.20795, 0.53089, 0.33478, 0.71528, 0.46014, 1, 0.66554, 1, 0.8685, 1, 1, 0.59296, 1, 0.2847, 0.85803, 0.2357, 0.78472, 0.25603, 0.56024, 0.09471, 0.4231, 0, 0.22955, 0, 0, 0.09776, 0, 0.88632, 0.58353, 0.74383, 0.78582, 0.53502, 0.62672, 0.38622, 0.45345, 0.22815, 0.31327 ],
				"triangles": [ 6, 15, 5, 15, 14, 3, 15, 4, 5, 15, 3, 4, 13, 18, 12, 18, 11, 12, 10, 11, 18, 0, 18, 13, 10, 18, 9, 9, 18, 17, 18, 0, 17, 17, 0, 1, 7, 16, 6, 6, 16, 15, 7, 8, 16, 16, 8, 9, 16, 2, 15, 15, 2, 14, 9, 17, 16, 17, 1, 16, 16, 1, 2 ],
				"vertices": [ 2, 14, 92.27, -23.2, 0.22, 23, 25.92, -13.65, 0.78, 2, 14, 71.01, -20.66, 0.5, 23, 5.32, -19.5, 0.5, 3, 14, 49.17, -18.77, 0.6864, 23, -15.55, -26.17, 0.1936, 6, 3.99, 53.51, 0.12, 1, 6, 34.32, 36.48, 1, 1, 6, 39.99, 13.63, 1, 1, 6, 43.66, -1.17, 1, 2, 14, 20.57, 37.99, 0.52999, 6, 8.49, -9.89, 0.47, 3, 14, 52.42, 41.13, 0.6864, 23, -35.63, 30.36, 0.1936, 6, -22.09, -0.5, 0.12, 2, 14, 60.99, 36.9, 0.62, 23, -26.09, 29.75, 0.38, 2, 14, 75.06, 14.91, 0.5, 23, -4.64, 14.89, 0.5, 2, 14, 96.07, 10.7, 0.22, 23, 16.37, 19.09, 0.78, 1, 23, 39.97, 14.86, 1, 1, 23, 62.86, 1.24, 1, 1, 23, 58.41, -6.23, 1, 2, 14, 28.41, -16.35, 0.52999, 6, 22.21, 43.28, 0.47, 2, 14, 24.6, 10.04, 0.52999, 6, 15.55, 17.45, 0.47, 3, 14, 50.53, 6.3, 0.6864, 23, -23.96, -2.5, 0.1936, 6, -6.92, 30.89, 0.12, 2, 14, 73.14, -1.93, 0.5, 23, 0.08, -1.4, 0.5, 2, 14, 94.13, -6.6, 0.22, 23, 21.24, 2.37, 0.78 ],
				"hull": 14,
				"edges": [ 4, 2, 2, 0, 20, 18, 24, 26, 0, 26, 22, 24, 20, 22, 18, 16, 16, 14, 10, 12, 14, 12, 6, 28, 28, 4, 6, 8, 8, 10, 12, 30, 30, 28, 8, 30, 4, 32, 32, 14, 30, 32, 2, 34, 34, 18, 32, 34, 0, 36, 36, 20, 34, 36, 36, 24, 4, 6 ],
				"width": 89,
				"height": 116
			}
		}
	}
},
"events": {
	"callback": {}
},
"animations": {
	"atk1": {
		"slots": {
			"chibang12": {
				"attachment": [
					{ "time": 0, "name": "chibang1" }
				]
			},
			"chibang22": {
				"attachment": [
					{ "time": 0, "name": "chibang2" }
				]
			},
			"daizi12": {
				"attachment": [
					{ "time": 0, "name": "daizi1" }
				]
			},
			"daizi22": {
				"attachment": [
					{ "time": 0, "name": "daizi2" }
				]
			},
			"gongji/qiangkou/qiangkou018": {
				"attachment": [
					{ "time": 0, "name": null },
					{ "time": 0.6, "name": "gongji/qiangkou/qiangkou018" },
					{ "time": 0.6333, "name": "gongji/qiangkou/qiangkou019" },
					{ "time": 0.6666, "name": "gongji/qiangkou/qiangkou020" },
					{ "time": 0.7, "name": "gongji/qiangkou/qiangkou021" },
					{ "time": 0.7333, "name": null }
				]
			},
			"gongji/qiangkou/qiangkou0182": {
				"attachment": [
					{ "time": 0, "name": null },
					{ "time": 0.6, "name": "gongji/qiangkou/qiangkou018" },
					{ "time": 0.6333, "name": "gongji/qiangkou/qiangkou019" },
					{ "time": 0.6666, "name": "gongji/qiangkou/qiangkou020" },
					{ "time": 0.7, "name": "gongji/qiangkou/qiangkou021" },
					{ "time": 0.7333, "name": null }
				]
			},
			"jiao12": {
				"attachment": [
					{ "time": 0, "name": "jiao1" }
				]
			},
			"jiao22": {
				"attachment": [
					{ "time": 0, "name": "jiao2" }
				]
			},
			"jineng/zhuaji019": {
				"attachment": [
					{ "time": 0, "name": null }
				]
			},
			"shenti2": {
				"attachment": [
					{ "time": 0, "name": "shenti" }
				]
			},
			"weiba2": {
				"attachment": [
					{ "time": 0, "name": "weiba" }
				]
			},
			"yumao2": {
				"attachment": [
					{ "time": 0, "name": "yumao2" }
				]
			},
			"yumao12": {
				"attachment": [
					{ "time": 0, "name": "yumao1" }
				]
			},
			"yumao32": {
				"attachment": [
					{ "time": 0, "name": "yumao3" }
				]
			}
		},
		"bones": {
			"root": {
				"rotate": [
					{ "time": 0, "angle": 0, "curve": "stepped" },
					{ "time": 0.2333, "angle": 0, "curve": "stepped" },
					{ "time": 0.5, "angle": 0, "curve": "stepped" },
					{ "time": 0.6, "angle": 0, "curve": "stepped" },
					{ "time": 1.0666, "angle": 0 }
				],
				"translate": [
					{ "time": 0, "x": 0, "y": 0, "curve": "stepped" },
					{ "time": 0.2333, "x": 0, "y": 0, "curve": "stepped" },
					{ "time": 0.5, "x": 0, "y": 0, "curve": "stepped" },
					{ "time": 0.6, "x": 0, "y": 0, "curve": "stepped" },
					{ "time": 1.0666, "x": 0, "y": 0 }
				],
				"scale": [
					{ "time": 0, "x": 0.999, "y": 0.999, "curve": "stepped" },
					{ "time": 0.2333, "x": 0.999, "y": 0.999, "curve": "stepped" },
					{ "time": 0.5, "x": 0.999, "y": 0.999, "curve": "stepped" },
					{ "time": 0.6, "x": 0.999, "y": 0.999, "curve": "stepped" },
					{ "time": 1.0666, "x": 0.999, "y": 0.999 }
				]
			},
			"bone": {
				"rotate": [
					{
						"time": 0,
						"angle": 0,
						"curve": [ 0.25, 0, 0.75, 1 ]
					},
					{
						"time": 0.2333,
						"angle": 8.03,
						"curve": [ 0.25, 0, 0.75, 1 ]
					},
					{
						"time": 0.5,
						"angle": 38.67,
						"curve": [ 0.25, 0, 0.75, 1 ]
					},
					{
						"time": 0.6,
						"angle": -14.22,
						"curve": [ 0.25, 0, 0.75, 1 ]
					},
					{
						"time": 0.8,
						"angle": 2.32,
						"curve": [ 0.25, 0, 0.75, 1 ]
					},
					{ "time": 1.0666, "angle": 0 }
				],
				"translate": [
					{
						"time": 0,
						"x": 0,
						"y": 0,
						"curve": [ 0.25, 0, 0.75, 1 ]
					},
					{
						"time": 0.2333,
						"x": -82.03,
						"y": 0,
						"curve": [ 0.25, 0, 0.75, 1 ]
					},
					{
						"time": 0.5,
						"x": -139.42,
						"y": 4.99,
						"curve": [ 0.25, 0, 0.75, 1 ]
					},
					{
						"time": 0.6,
						"x": 129.65,
						"y": 4.99,
						"curve": [ 0.25, 0, 0.75, 1 ]
					},
					{
						"time": 0.6666,
						"x": 153.54,
						"y": 4.99,
						"curve": [ 0.25, 0, 0.75, 1 ]
					},
					{
						"time": 0.8,
						"x": 129.65,
						"y": 4.99,
						"curve": [ 0.25, 0, 0.75, 1 ]
					},
					{ "time": 1.0666, "x": 0, "y": 0 }
				],
				"scale": [
					{ "time": 0, "x": 1, "y": 1, "curve": "stepped" },
					{ "time": 0.2333, "x": 1, "y": 1, "curve": "stepped" },
					{ "time": 0.5, "x": 1, "y": 1, "curve": "stepped" },
					{ "time": 0.6, "x": 1, "y": 1, "curve": "stepped" },
					{ "time": 0.8, "x": 1, "y": 1, "curve": "stepped" },
					{ "time": 1.0666, "x": 1, "y": 1 }
				]
			},
			"bone12": {
				"rotate": [
					{
						"time": 0,
						"angle": 0,
						"curve": [ 0.25, 0, 0.75, 1 ]
					},
					{
						"time": 0.2333,
						"angle": -11.44,
						"curve": [ 0.25, 0, 0.75, 1 ]
					},
					{
						"time": 0.5,
						"angle": 50.45,
						"curve": [ 0.25, 0, 0.75, 1 ]
					},
					{
						"time": 0.6,
						"angle": 49.06,
						"curve": [ 0.25, 0, 0.75, 1 ]
					},
					{
						"time": 0.6666,
						"angle": -11.44,
						"curve": [ 0.25, 0, 0.75, 1 ]
					},
					{
						"time": 0.8,
						"angle": 316.83,
						"curve": [ 0.25, 0, 0.75, 1 ]
					},
					{ "time": 1.0666, "angle": 0 }
				],
				"translate": [
					{ "time": 0, "x": 0, "y": 0, "curve": "stepped" },
					{ "time": 0.2333, "x": 0, "y": 0, "curve": "stepped" },
					{ "time": 0.5, "x": 0, "y": 0, "curve": "stepped" },
					{
						"time": 0.6,
						"x": 0,
						"y": 0,
						"curve": [ 0.25, 0, 0.75, 1 ]
					},
					{
						"time": 0.7333,
						"x": 10.15,
						"y": 8.31,
						"curve": [ 0.25, 0, 0.75, 1 ]
					},
					{ "time": 0.8666, "x": 0, "y": 0, "curve": "stepped" },
					{ "time": 1.0666, "x": 0, "y": 0 }
				],
				"scale": [
					{ "time": 0, "x": 1, "y": 1, "curve": "stepped" },
					{ "time": 0.2333, "x": 1, "y": 1, "curve": "stepped" },
					{ "time": 0.5, "x": 1, "y": 1, "curve": "stepped" },
					{ "time": 0.6, "x": 1, "y": 1, "curve": "stepped" },
					{ "time": 1.0666, "x": 1, "y": 1 }
				]
			},
			"bone2": {
				"rotate": [
					{
						"time": 0,
						"angle": 0,
						"curve": [ 0.25, 0, 0.75, 1 ]
					},
					{
						"time": 0.2333,
						"angle": -6.69,
						"curve": [ 0.25, 0, 0.75, 1 ]
					},
					{
						"time": 0.5666,
						"angle": 9.96,
						"curve": [ 0.25, 0, 0.75, 1 ]
					},
					{
						"time": 0.6,
						"angle": -25.55,
						"curve": [ 0.25, 0, 0.75, 1 ]
					},
					{
						"time": 0.7,
						"angle": -49.09,
						"curve": [ 0.25, 0, 0.75, 1 ]
					},
					{
						"time": 0.8,
						"angle": -39.22,
						"curve": [ 0.25, 0, 0.75, 1 ]
					},
					{ "time": 1.0666, "angle": 0 }
				],
				"translate": [
					{
						"time": 0,
						"x": 0,
						"y": 0,
						"curve": [ 0.25, 0, 0.75, 1 ]
					},
					{
						"time": 0.2333,
						"x": -9.05,
						"y": -3.04,
						"curve": [ 0.25, 0, 0.75, 1 ]
					},
					{
						"time": 0.5666,
						"x": 6.69,
						"y": 32.65,
						"curve": [ 0.25, 0, 0.75, 1 ]
					},
					{
						"time": 0.6,
						"x": -25.47,
						"y": 1.42,
						"curve": [ 0.25, 0, 0.75, 1 ]
					},
					{
						"time": 0.7,
						"x": -17.96,
						"y": 1.93,
						"curve": [ 0.25, 0, 0.75, 1 ]
					},
					{
						"time": 0.8333,
						"x": -25.47,
						"y": 1.42,
						"curve": [ 0.25, 0, 0.75, 1 ]
					},
					{ "time": 1.0666, "x": 0, "y": 0 }
				],
				"scale": [
					{ "time": 0, "x": 1, "y": 1, "curve": "stepped" },
					{ "time": 0.2333, "x": 1, "y": 1, "curve": "stepped" },
					{ "time": 0.5666, "x": 1, "y": 1, "curve": "stepped" },
					{ "time": 0.6, "x": 1, "y": 1, "curve": "stepped" },
					{ "time": 0.9, "x": 1, "y": 1, "curve": "stepped" },
					{ "time": 1.0666, "x": 1, "y": 1 }
				]
			},
			"bone22": {
				"rotate": [
					{ "time": 0, "angle": 0, "curve": "stepped" },
					{
						"time": 0.2333,
						"angle": 0,
						"curve": [ 0.25, 0, 0.75, 1 ]
					},
					{
						"time": 0.5,
						"angle": 39.55,
						"curve": [ 0.25, 0, 0.75, 1 ]
					},
					{
						"time": 0.6,
						"angle": 0,
						"curve": [ 0.25, 0, 0.75, 1 ]
					},
					{
						"time": 0.8333,
						"angle": 23.94,
						"curve": [ 0.25, 0, 0.75, 1 ]
					},
					{ "time": 1.0666, "angle": 0 }
				],
				"translate": [
					{ "time": 0, "x": 0, "y": 0, "curve": "stepped" },
					{ "time": 0.2333, "x": 0, "y": 0, "curve": "stepped" },
					{ "time": 0.5, "x": 0, "y": 0, "curve": "stepped" },
					{ "time": 0.6, "x": 0, "y": 0, "curve": "stepped" },
					{ "time": 1.0666, "x": 0, "y": 0 }
				],
				"scale": [
					{ "time": 0, "x": 1, "y": 1, "curve": "stepped" },
					{ "time": 0.2333, "x": 1, "y": 1, "curve": "stepped" },
					{ "time": 0.5, "x": 1, "y": 1, "curve": "stepped" },
					{ "time": 0.6, "x": 1, "y": 1, "curve": "stepped" },
					{ "time": 1.0666, "x": 1, "y": 1 }
				]
			},
			"bone3": {
				"rotate": [
					{ "time": 0, "angle": 0, "curve": "stepped" },
					{ "time": 0.2333, "angle": 0, "curve": "stepped" },
					{ "time": 0.5, "angle": 0, "curve": "stepped" },
					{ "time": 0.6, "angle": 0, "curve": "stepped" },
					{ "time": 1.0666, "angle": 0 }
				],
				"translate": [
					{ "time": 0, "x": 0, "y": 0, "curve": "stepped" },
					{ "time": 0.2333, "x": 0, "y": 0, "curve": "stepped" },
					{ "time": 0.5, "x": 0, "y": 0, "curve": "stepped" },
					{ "time": 0.6, "x": 0, "y": 0, "curve": "stepped" },
					{ "time": 1.0666, "x": 0, "y": 0 }
				],
				"scale": [
					{ "time": 0, "x": 1, "y": 1, "curve": "stepped" },
					{ "time": 0.2333, "x": 1, "y": 1, "curve": "stepped" },
					{ "time": 0.5, "x": 1, "y": 1, "curve": "stepped" },
					{ "time": 0.6, "x": 1, "y": 1, "curve": "stepped" },
					{ "time": 1.0666, "x": 1, "y": 1 }
				]
			},
			"bone8": {
				"rotate": [
					{
						"time": 0,
						"angle": 0,
						"curve": [ 0.25, 0, 0.75, 1 ]
					},
					{
						"time": 0.2333,
						"angle": -30.39,
						"curve": [ 0.25, 0, 0.75, 1 ]
					},
					{ "time": 0.5, "angle": 32.14, "curve": "stepped" },
					{
						"time": 0.6,
						"angle": 32.14,
						"curve": [ 0.25, 0, 0.75, 1 ]
					},
					{
						"time": 0.7333,
						"angle": -17.09,
						"curve": [ 0.25, 0, 0.75, 1 ]
					},
					{
						"time": 0.9,
						"angle": -30.83,
						"curve": [ 0.25, 0, 0.75, 1 ]
					},
					{ "time": 1.0666, "angle": 0 }
				],
				"translate": [
					{ "time": 0, "x": 0, "y": 0, "curve": "stepped" },
					{ "time": 0.2333, "x": 0, "y": 0, "curve": "stepped" },
					{ "time": 0.5, "x": 0, "y": 0, "curve": "stepped" },
					{ "time": 0.6, "x": 0, "y": 0, "curve": "stepped" },
					{ "time": 1.0666, "x": 0, "y": 0 }
				],
				"scale": [
					{ "time": 0, "x": 1, "y": 1, "curve": "stepped" },
					{ "time": 0.2333, "x": 1, "y": 1, "curve": "stepped" },
					{ "time": 0.5, "x": 1, "y": 1, "curve": "stepped" },
					{ "time": 0.6, "x": 1, "y": 1, "curve": "stepped" },
					{ "time": 1.0666, "x": 1, "y": 1 }
				]
			},
			"bone9": {
				"rotate": [
					{
						"time": 0,
						"angle": 0,
						"curve": [ 0.25, 0, 0.75, 1 ]
					},
					{
						"time": 0.2,
						"angle": -10.72,
						"curve": [ 0.25, 0, 0.75, 1 ]
					},
					{
						"time": 0.4333,
						"angle": 28.01,
						"curve": [ 0.25, 0, 0.75, 1 ]
					},
					{
						"time": 0.7,
						"angle": -10.06,
						"curve": [ 0.25, 0, 0.75, 1 ]
					},
					{
						"time": 0.9,
						"angle": -4.34,
						"curve": [ 0.25, 0, 0.75, 1 ]
					},
					{ "time": 1.0666, "angle": 0 }
				],
				"translate": [
					{ "time": 0, "x": 0, "y": 0, "curve": "stepped" },
					{ "time": 1.0666, "x": 0, "y": 0 }
				],
				"scale": [
					{ "time": 0, "x": 1, "y": 1, "curve": "stepped" },
					{ "time": 1.0666, "x": 1, "y": 1 }
				]
			},
			"bone10": {
				"rotate": [
					{
						"time": 0,
						"angle": 0,
						"curve": [ 0.25, 0, 0.75, 1 ]
					},
					{
						"time": 0.1333,
						"angle": 29.13,
						"curve": [ 0.25, 0, 0.75, 1 ]
					},
					{
						"time": 0.3666,
						"angle": -51.49,
						"curve": [ 0.25, 0, 0.75, 1 ]
					},
					{
						"time": 0.6333,
						"angle": 20.73,
						"curve": [ 0.25, 0, 0.75, 1 ]
					},
					{
						"time": 0.8333,
						"angle": -49.65,
						"curve": [ 0.25, 0, 0.75, 1 ]
					},
					{ "time": 1.0666, "angle": 0 }
				],
				"translate": [
					{ "time": 0, "x": 0, "y": 0, "curve": "stepped" },
					{ "time": 1.0666, "x": 0, "y": 0 }
				],
				"scale": [
					{ "time": 0, "x": 1, "y": 1, "curve": "stepped" },
					{ "time": 1.0666, "x": 1, "y": 1 }
				]
			},
			"bone13": {
				"rotate": [
					{
						"time": 0,
						"angle": 0,
						"curve": [ 0.25, 0, 0.75, 1 ]
					},
					{ "time": 0.2333, "angle": 27.47, "curve": "stepped" },
					{ "time": 0.5, "angle": 27.47, "curve": "stepped" },
					{
						"time": 0.6,
						"angle": 27.47,
						"curve": [ 0.25, 0, 0.75, 1 ]
					},
					{
						"time": 0.7333,
						"angle": -55.52,
						"curve": [ 0.25, 0, 0.75, 1 ]
					},
					{ "time": 1.0666, "angle": 0 }
				],
				"translate": [
					{ "time": 0, "x": 0, "y": 0, "curve": "stepped" },
					{ "time": 0.2333, "x": 0, "y": 0, "curve": "stepped" },
					{ "time": 0.5, "x": 0, "y": 0, "curve": "stepped" },
					{ "time": 0.6, "x": 0, "y": 0, "curve": "stepped" },
					{ "time": 1.0666, "x": 0, "y": 0 }
				],
				"scale": [
					{ "time": 0, "x": 1, "y": 1, "curve": "stepped" },
					{ "time": 0.2333, "x": 1, "y": 1, "curve": "stepped" },
					{ "time": 0.5, "x": 1, "y": 1, "curve": "stepped" },
					{ "time": 0.6, "x": 1, "y": 1, "curve": "stepped" },
					{ "time": 1.0666, "x": 1, "y": 1 }
				]
			},
			"bone14": {
				"rotate": [
					{
						"time": 0,
						"angle": 0,
						"curve": [ 0.25, 0, 0.75, 1 ]
					},
					{ "time": 0.2333, "angle": -12.76, "curve": "stepped" },
					{
						"time": 0.5,
						"angle": -12.76,
						"curve": [ 0.25, 0, 0.75, 1 ]
					},
					{
						"time": 0.6,
						"angle": -46.4,
						"curve": [ 0.25, 0, 0.75, 1 ]
					},
					{
						"time": 0.7333,
						"angle": 16.57,
						"curve": [ 0.25, 0, 0.75, 1 ]
					},
					{ "time": 1.0666, "angle": 0 }
				],
				"translate": [
					{ "time": 0, "x": 0, "y": 0, "curve": "stepped" },
					{ "time": 0.2333, "x": 0, "y": 0, "curve": "stepped" },
					{ "time": 0.5, "x": 0, "y": 0, "curve": "stepped" },
					{ "time": 0.6, "x": 0, "y": 0, "curve": "stepped" },
					{ "time": 1.0666, "x": 0, "y": 0 }
				],
				"scale": [
					{ "time": 0, "x": 1, "y": 1, "curve": "stepped" },
					{ "time": 0.2333, "x": 1, "y": 1, "curve": "stepped" },
					{ "time": 0.5, "x": 1, "y": 1, "curve": "stepped" },
					{ "time": 0.6, "x": 1, "y": 1, "curve": "stepped" },
					{ "time": 1.0666, "x": 1, "y": 1 }
				]
			},
			"bone15": {
				"rotate": [
					{
						"time": 0,
						"angle": 0,
						"curve": [ 0.25, 0, 0.75, 1 ]
					},
					{
						"time": 0.2333,
						"angle": -0.53,
						"curve": [ 0.25, 0, 0.75, 1 ]
					},
					{
						"time": 0.5,
						"angle": 2.83,
						"curve": [ 0.25, 0, 0.75, 1 ]
					},
					{
						"time": 0.6333,
						"angle": -7.04,
						"curve": [ 0.25, 0, 0.75, 1 ]
					},
					{
						"time": 0.8,
						"angle": -13.47,
						"curve": [ 0.25, 0, 0.75, 1 ]
					},
					{ "time": 1.0666, "angle": 0 }
				],
				"translate": [
					{ "time": 0, "x": 0, "y": 0, "curve": "stepped" },
					{ "time": 1.0666, "x": 0, "y": 0 }
				],
				"scale": [
					{ "time": 0, "x": 1, "y": 1, "curve": "stepped" },
					{ "time": 1.0666, "x": 1, "y": 1 }
				]
			},
			"bone17": {
				"rotate": [
					{
						"time": 0,
						"angle": 0,
						"curve": [ 0.25, 0, 0.75, 1 ]
					},
					{
						"time": 0.2666,
						"angle": -26.31,
						"curve": [ 0.25, 0, 0.75, 1 ]
					},
					{
						"time": 0.5666,
						"angle": -312.19,
						"curve": [ 0.25, 0, 0.75, 1 ]
					},
					{
						"time": 0.7333,
						"angle": -6.52,
						"curve": [ 0.25, 0, 0.75, 1 ]
					},
					{ "time": 1.0666, "angle": 0 }
				],
				"translate": [
					{ "time": 0, "x": 0, "y": 0, "curve": "stepped" },
					{ "time": 1.0666, "x": 0, "y": 0 }
				],
				"scale": [
					{ "time": 0, "x": 1, "y": 1, "curve": "stepped" },
					{ "time": 1.0666, "x": 1, "y": 1 }
				]
			},
			"bone18": {
				"rotate": [
					{
						"time": 0,
						"angle": 0,
						"curve": [ 0.25, 0, 0.75, 1 ]
					},
					{
						"time": 0.2666,
						"angle": 30.79,
						"curve": [ 0.25, 0, 0.75, 1 ]
					},
					{
						"time": 0.5333,
						"angle": -18.6,
						"curve": [ 0.25, 0, 0.75, 1 ]
					},
					{ "time": 1.0666, "angle": 0 }
				],
				"translate": [
					{ "time": 0, "x": 0, "y": 0, "curve": "stepped" },
					{ "time": 1.0666, "x": 0, "y": 0 }
				],
				"scale": [
					{ "time": 0, "x": 1, "y": 1, "curve": "stepped" },
					{ "time": 1.0666, "x": 1, "y": 1 }
				]
			},
			"bone19": {
				"rotate": [
					{
						"time": 0,
						"angle": 0,
						"curve": [ 0.25, 0, 0.75, 1 ]
					},
					{
						"time": 0.3,
						"angle": -16.39,
						"curve": [ 0.25, 0, 0.75, 1 ]
					},
					{
						"time": 0.5333,
						"angle": -10.94,
						"curve": [ 0.25, 0, 0.75, 1 ]
					},
					{
						"time": 0.7333,
						"angle": 0.64,
						"curve": [ 0.25, 0, 0.75, 1 ]
					},
					{ "time": 1.0666, "angle": 0 }
				],
				"translate": [
					{ "time": 0, "x": 0, "y": 0, "curve": "stepped" },
					{ "time": 1.0666, "x": 0, "y": 0 }
				],
				"scale": [
					{ "time": 0, "x": 1, "y": 1, "curve": "stepped" },
					{ "time": 1.0666, "x": 1, "y": 1 }
				]
			},
			"bone21": {
				"rotate": [
					{
						"time": 0,
						"angle": 0,
						"curve": [ 0.25, 0, 0.75, 1 ]
					},
					{
						"time": 0.2,
						"angle": 30.97,
						"curve": [ 0.25, 0, 0.75, 1 ]
					},
					{
						"time": 0.6,
						"angle": -38.25,
						"curve": [ 0.25, 0, 0.75, 1 ]
					},
					{
						"time": 0.8333,
						"angle": 21.23,
						"curve": [ 0.25, 0, 0.75, 1 ]
					},
					{ "time": 1.0666, "angle": 0 }
				],
				"translate": [
					{ "time": 0, "x": 0, "y": 0, "curve": "stepped" },
					{ "time": 1.0666, "x": 0, "y": 0 }
				],
				"scale": [
					{ "time": 0, "x": 1, "y": 1, "curve": "stepped" },
					{ "time": 1.0666, "x": 1, "y": 1 }
				]
			},
			"bone23": {
				"rotate": [
					{ "time": 0, "angle": 0, "curve": "stepped" },
					{ "time": 0.2333, "angle": 0, "curve": "stepped" },
					{ "time": 0.5, "angle": 0, "curve": "stepped" },
					{ "time": 0.6, "angle": 0, "curve": "stepped" },
					{ "time": 1.0666, "angle": 0 }
				],
				"translate": [
					{ "time": 0, "x": 0, "y": 0, "curve": "stepped" },
					{ "time": 0.2333, "x": 0, "y": 0, "curve": "stepped" },
					{ "time": 0.5, "x": 0, "y": 0, "curve": "stepped" },
					{ "time": 0.6, "x": 0, "y": 0, "curve": "stepped" },
					{ "time": 1.0666, "x": 0, "y": 0 }
				],
				"scale": [
					{ "time": 0, "x": 1, "y": 1, "curve": "stepped" },
					{ "time": 0.2333, "x": 1, "y": 1, "curve": "stepped" },
					{ "time": 0.5, "x": 1, "y": 1, "curve": "stepped" },
					{ "time": 0.6, "x": 1, "y": 1, "curve": "stepped" },
					{ "time": 1.0666, "x": 1, "y": 1 }
				]
			},
			"bone24": {
				"rotate": [
					{
						"time": 0,
						"angle": 0,
						"curve": [ 0.25, 0, 0.75, 1 ]
					},
					{ "time": 0.2333, "angle": 1.66, "curve": "stepped" },
					{ "time": 0.5, "angle": 1.66, "curve": "stepped" },
					{
						"time": 0.6,
						"angle": 1.66,
						"curve": [ 0.25, 0, 0.75, 1 ]
					},
					{ "time": 1.0666, "angle": 0 }
				],
				"translate": [
					{ "time": 0, "x": 0, "y": 0, "curve": "stepped" },
					{ "time": 0.2333, "x": 0, "y": 0, "curve": "stepped" },
					{ "time": 0.5, "x": 0, "y": 0, "curve": "stepped" },
					{ "time": 0.6, "x": 0, "y": 0, "curve": "stepped" },
					{ "time": 1.0666, "x": 0, "y": 0 }
				],
				"scale": [
					{ "time": 0, "x": 1, "y": 1, "curve": "stepped" },
					{ "time": 0.2333, "x": 1, "y": 1, "curve": "stepped" },
					{ "time": 0.5, "x": 1, "y": 1, "curve": "stepped" },
					{ "time": 0.6, "x": 1, "y": 1, "curve": "stepped" },
					{ "time": 1.0666, "x": 1, "y": 1 }
				]
			},
			"bone4": {
				"rotate": [
					{
						"time": 0,
						"angle": 0,
						"curve": [ 0.25, 0, 0.75, 1 ]
					},
					{
						"time": 0.2333,
						"angle": 16.66,
						"curve": [ 0.25, 0, 0.75, 1 ]
					},
					{ "time": 0.5, "angle": -33.27, "curve": "stepped" },
					{
						"time": 0.6,
						"angle": -33.27,
						"curve": [ 0.25, 0, 0.75, 1 ]
					},
					{
						"time": 0.7,
						"angle": 35.78,
						"curve": [ 0.25, 0, 0.75, 1 ]
					},
					{ "time": 1.0666, "angle": 0 }
				],
				"translate": [
					{ "time": 0, "x": 0, "y": 0, "curve": "stepped" },
					{ "time": 0.2333, "x": 0, "y": 0, "curve": "stepped" },
					{ "time": 0.5, "x": 0, "y": 0, "curve": "stepped" },
					{ "time": 0.6, "x": 0, "y": 0, "curve": "stepped" },
					{ "time": 1.0666, "x": 0, "y": 0 }
				],
				"scale": [
					{ "time": 0, "x": 1, "y": 1, "curve": "stepped" },
					{ "time": 0.2333, "x": 1, "y": 1, "curve": "stepped" },
					{ "time": 0.5, "x": 1, "y": 1, "curve": "stepped" },
					{ "time": 0.6, "x": 1, "y": 1, "curve": "stepped" },
					{ "time": 1.0666, "x": 1, "y": 1 }
				]
			},
			"bone11": {
				"rotate": [
					{
						"time": 0,
						"angle": 0,
						"curve": [ 0.25, 0, 0.75, 1 ]
					},
					{
						"time": 0.2,
						"angle": 31.43,
						"curve": [ 0.25, 0, 0.75, 1 ]
					},
					{
						"time": 0.4333,
						"angle": -29.94,
						"curve": [ 0.25, 0, 0.75, 1 ]
					},
					{
						"time": 0.7,
						"angle": 42.31,
						"curve": [ 0.25, 0, 0.75, 1 ]
					},
					{
						"time": 0.9,
						"angle": -27.43,
						"curve": [ 0.25, 0, 0.75, 1 ]
					},
					{ "time": 1.0666, "angle": 0 }
				],
				"translate": [
					{ "time": 0, "x": 0, "y": 0, "curve": "stepped" },
					{ "time": 1.0666, "x": 0, "y": 0 }
				],
				"scale": [
					{ "time": 0, "x": 1, "y": 1, "curve": "stepped" },
					{ "time": 1.0666, "x": 1, "y": 1 }
				]
			},
			"bone16": {
				"rotate": [
					{
						"time": 0,
						"angle": 0,
						"curve": [ 0.25, 0, 0.75, 1 ]
					},
					{
						"time": 0.2333,
						"angle": -28.73,
						"curve": [ 0.25, 0, 0.75, 1 ]
					},
					{
						"time": 0.5,
						"angle": 33.75,
						"curve": [ 0.25, 0, 0.75, 1 ]
					},
					{
						"time": 0.6333,
						"angle": 64.66,
						"curve": [ 0.25, 0, 0.75, 1 ]
					},
					{
						"time": 0.8,
						"angle": -15.1,
						"curve": [ 0.25, 0, 0.75, 1 ]
					},
					{ "time": 1.0666, "angle": 0 }
				],
				"translate": [
					{ "time": 0, "x": 0, "y": 0, "curve": "stepped" },
					{ "time": 1.0666, "x": 0, "y": 0 }
				],
				"scale": [
					{ "time": 0, "x": 1, "y": 1, "curve": "stepped" },
					{ "time": 1.0666, "x": 1, "y": 1 }
				]
			},
			"bone20": {
				"rotate": [
					{
						"time": 0,
						"angle": 0,
						"curve": [ 0.25, 0, 0.75, 1 ]
					},
					{
						"time": 0.2666,
						"angle": 77.46,
						"curve": [ 0.25, 0, 0.75, 1 ]
					},
					{
						"time": 0.5333,
						"angle": -6.02,
						"curve": [ 0.25, 0, 0.75, 1 ]
					},
					{
						"time": 0.7333,
						"angle": 76,
						"curve": [ 0.25, 0, 0.75, 1 ]
					},
					{ "time": 1.0666, "angle": 0 }
				],
				"translate": [
					{ "time": 0, "x": 0, "y": 0, "curve": "stepped" },
					{ "time": 1.0666, "x": 0, "y": 0 }
				],
				"scale": [
					{ "time": 0, "x": 1, "y": 1, "curve": "stepped" },
					{ "time": 1.0666, "x": 1, "y": 1 }
				]
			},
			"bone5": {
				"rotate": [
					{
						"time": 0,
						"angle": 0,
						"curve": [ 0.25, 0, 0.75, 1 ]
					},
					{
						"time": 0.2,
						"angle": 1.74,
						"curve": [ 0.25, 0, 0.75, 1 ]
					},
					{
						"time": 0.4333,
						"angle": 13.15,
						"curve": [ 0.25, 0, 0.75, 1 ]
					},
					{
						"time": 0.5333,
						"angle": -19.98,
						"curve": [ 0.25, 0, 0.75, 1 ]
					},
					{
						"time": 0.5666,
						"angle": -26.16,
						"curve": [ 0.25, 0, 0.75, 1 ]
					},
					{
						"time": 0.9,
						"angle": -37.29,
						"curve": [ 0.25, 0, 0.75, 1 ]
					},
					{ "time": 1.0666, "angle": 0 }
				],
				"translate": [
					{ "time": 0, "x": 0, "y": 0, "curve": "stepped" },
					{ "time": 1.0666, "x": 0, "y": 0 }
				],
				"scale": [
					{ "time": 0, "x": 1, "y": 1, "curve": "stepped" },
					{ "time": 1.0666, "x": 1, "y": 1 }
				]
			},
			"bone7": {
				"rotate": [
					{ "time": 0, "angle": 0, "curve": "stepped" },
					{ "time": 1.0666, "angle": 0 }
				],
				"translate": [
					{ "time": 0, "x": 0, "y": 0, "curve": "stepped" },
					{ "time": 1.0666, "x": 0, "y": 0 }
				],
				"scale": [
					{ "time": 0, "x": 1, "y": 1, "curve": "stepped" },
					{ "time": 1.0666, "x": 1, "y": 1 }
				]
			},
			"bone6": {
				"rotate": [
					{
						"time": 0,
						"angle": 0,
						"curve": [ 0.25, 0, 0.75, 1 ]
					},
					{
						"time": 0.2,
						"angle": -23.65,
						"curve": [ 0.25, 0, 0.75, 1 ]
					},
					{
						"time": 0.4333,
						"angle": 27.64,
						"curve": [ 0.25, 0, 0.75, 1 ]
					},
					{
						"time": 0.5333,
						"angle": -26.85,
						"curve": [ 0.25, 0, 0.75, 1 ]
					},
					{
						"time": 0.5666,
						"angle": -25.38,
						"curve": [ 0.25, 0, 0.75, 1 ]
					},
					{
						"time": 0.8333,
						"angle": 23.95,
						"curve": [ 0.25, 0, 0.75, 1 ]
					},
					{ "time": 1.0666, "angle": 0 }
				],
				"translate": [
					{ "time": 0, "x": 0, "y": 0, "curve": "stepped" },
					{ "time": 1.0666, "x": 0, "y": 0 }
				],
				"scale": [
					{ "time": 0, "x": 1, "y": 1, "curve": "stepped" },
					{ "time": 1.0666, "x": 1, "y": 1 }
				]
			},
			"bone26": {
				"translate": [
					{ "time": 0.6, "x": -490.24, "y": -76.12 }
				],
				"scale": [
					{ "time": 0.6, "x": 2.5, "y": 2.5 }
				]
			},
			"bone29": {
				"translate": [
					{ "time": 0.6, "x": -557.23, "y": -267.95 }
				],
				"scale": [
					{ "time": 0.6, "x": 2.5, "y": 2.5 }
				]
			},
			"bone28": {
				"translate": [
					{ "time": 0.8333, "x": 112.67, "y": 53.36 }
				]
			}
		},
		"ffd": {
			"default": {
				"chibang12": {
					"chibang1": [
						{ "time": 0 }
					]
				},
				"daizi12": {
					"daizi1": [
						{ "time": 0 }
					]
				},
				"daizi22": {
					"daizi2": [
						{ "time": 0 }
					]
				},
				"jiao12": {
					"jiao1": [
						{ "time": 0 }
					]
				},
				"jiao22": {
					"jiao2": [
						{ "time": 0 }
					]
				},
				"shenti2": {
					"shenti": [
						{ "time": 0 }
					]
				},
				"weiba2": {
					"weiba": [
						{ "time": 0 }
					]
				},
				"yumao2": {
					"yumao2": [
						{ "time": 0 }
					]
				},
				"yumao12": {
					"yumao1": [
						{ "time": 0 }
					]
				},
				"yumao32": {
					"yumao3": [
						{ "time": 0 }
					]
				}
			}
		},
		"drawOrder": [
			{ "time": 0 },
			{ "time": 0.8333 }
		],
		"events": [
			{ "time": 0.6, "name": "callback", "int": 1 }
		]
	},
	"atk2": {
		"slots": {
			"chibang12": {
				"attachment": [
					{ "time": 0, "name": "chibang1" }
				]
			},
			"chibang22": {
				"attachment": [
					{ "time": 0, "name": "chibang2" }
				]
			},
			"daizi12": {
				"attachment": [
					{ "time": 0, "name": "daizi1" }
				]
			},
			"daizi22": {
				"attachment": [
					{ "time": 0, "name": "daizi2" }
				]
			},
			"gongji/qiangkou/qiangkou018": {
				"attachment": [
					{ "time": 0, "name": null }
				]
			},
			"gongji/qiangkou/qiangkou0182": {
				"attachment": [
					{ "time": 0, "name": null }
				]
			},
			"jiao12": {
				"attachment": [
					{ "time": 0, "name": "jiao1" }
				]
			},
			"jiao22": {
				"attachment": [
					{ "time": 0, "name": "jiao2" }
				]
			},
			"jineng/zhuaji019": {
				"attachment": [
					{ "time": 0, "name": null },
					{ "time": 0.7, "name": "jineng/zhuaji019" },
					{ "time": 0.7333, "name": "jineng/zhuaji020" },
					{ "time": 0.7666, "name": "jineng/zhuaji022" },
					{ "time": 0.8, "name": "jineng/zhuaji022" },
					{ "time": 0.8333, "name": "jineng/zhuaji023" },
					{ "time": 0.8666, "name": "jineng/zhuaji024" },
					{ "time": 0.9, "name": null }
				]
			},
			"shenti2": {
				"attachment": [
					{ "time": 0, "name": "shenti" }
				]
			},
			"weiba2": {
				"attachment": [
					{ "time": 0, "name": "weiba" }
				]
			},
			"yumao2": {
				"attachment": [
					{ "time": 0, "name": "yumao2" }
				]
			},
			"yumao12": {
				"attachment": [
					{ "time": 0, "name": "yumao1" }
				]
			},
			"yumao32": {
				"attachment": [
					{ "time": 0, "name": "yumao3" }
				]
			}
		},
		"bones": {
			"root": {
				"rotate": [
					{ "time": 0, "angle": 0, "curve": "stepped" },
					{ "time": 0.2, "angle": 0, "curve": "stepped" },
					{ "time": 0.6666, "angle": 0, "curve": "stepped" },
					{ "time": 0.7666, "angle": 0 }
				],
				"translate": [
					{ "time": 0, "x": 0, "y": 0, "curve": "stepped" },
					{ "time": 0.2, "x": 0, "y": 0, "curve": "stepped" },
					{ "time": 0.6666, "x": 0, "y": 0, "curve": "stepped" },
					{ "time": 0.7666, "x": 0, "y": 0 }
				],
				"scale": [
					{ "time": 0, "x": 0.999, "y": 0.999, "curve": "stepped" },
					{ "time": 0.2, "x": 0.999, "y": 0.999, "curve": "stepped" },
					{ "time": 0.6666, "x": 0.999, "y": 0.999, "curve": "stepped" },
					{ "time": 0.7666, "x": 0.999, "y": 0.999 }
				]
			},
			"bone": {
				"rotate": [
					{
						"time": 0,
						"angle": 0,
						"curve": [ 0.25, 0, 0.75, 1 ]
					},
					{
						"time": 0.2,
						"angle": 52.63,
						"curve": [ 0.25, 0, 0.75, 1 ]
					},
					{ "time": 0.2666, "angle": 53.02, "curve": "stepped" },
					{ "time": 0.4, "angle": 53.02, "curve": "stepped" },
					{ "time": 0.5333, "angle": 53.02, "curve": "stepped" },
					{
						"time": 0.6666,
						"angle": 53.02,
						"curve": [ 0.25, 0, 0.75, 1 ]
					},
					{
						"time": 0.7666,
						"angle": -26.2,
						"curve": [ 0.25, 0, 0.75, 1 ]
					},
					{
						"time": 0.8666,
						"angle": -25.03,
						"curve": [ 0.25, 0, 0.75, 1 ]
					},
					{
						"time": 1.0333,
						"angle": -26.2,
						"curve": [ 0.25, 0, 0.75, 1 ]
					},
					{ "time": 1.3, "angle": 0 }
				],
				"translate": [
					{
						"time": 0,
						"x": 0,
						"y": 0,
						"curve": [ 0.25, 0, 0.75, 1 ]
					},
					{
						"time": 0.2,
						"x": 32.05,
						"y": -79.49,
						"curve": [ 0.25, 0, 0.75, 1 ]
					},
					{
						"time": 0.2666,
						"x": 22.58,
						"y": -57.49,
						"curve": [ 0.25, 0, 0.75, 1 ]
					},
					{
						"time": 0.3333,
						"x": 32.05,
						"y": -79.49,
						"curve": [ 0.25, 0, 0.75, 1 ]
					},
					{
						"time": 0.4,
						"x": 22.58,
						"y": -57.49,
						"curve": [ 0.25, 0, 0.75, 1 ]
					},
					{
						"time": 0.4666,
						"x": 32.05,
						"y": -79.49,
						"curve": [ 0.25, 0, 0.75, 1 ]
					},
					{
						"time": 0.5333,
						"x": 22.58,
						"y": -57.49,
						"curve": [ 0.25, 0, 0.75, 1 ]
					},
					{
						"time": 0.6,
						"x": 32.05,
						"y": -79.49,
						"curve": [ 0.25, 0, 0.75, 1 ]
					},
					{
						"time": 0.6666,
						"x": 22.58,
						"y": -57.49,
						"curve": [ 0.25, 0, 0.75, 1 ]
					},
					{
						"time": 0.7333,
						"x": 158.24,
						"y": 58.2,
						"curve": [ 0.25, 0, 0.75, 1 ]
					},
					{
						"time": 0.7666,
						"x": 0,
						"y": 0,
						"curve": [ 0.25, 0, 0.75, 1 ]
					},
					{
						"time": 0.8666,
						"x": 0,
						"y": 22.38,
						"curve": [ 0.25, 0, 0.75, 1 ]
					},
					{ "time": 1.0333, "x": 0, "y": 0, "curve": "stepped" },
					{ "time": 1.3, "x": 0, "y": 0 }
				],
				"scale": [
					{ "time": 0, "x": 1, "y": 1, "curve": "stepped" },
					{ "time": 0.2, "x": 1, "y": 1, "curve": "stepped" },
					{ "time": 0.2666, "x": 1, "y": 1, "curve": "stepped" },
					{ "time": 0.4, "x": 1, "y": 1, "curve": "stepped" },
					{ "time": 0.5333, "x": 1, "y": 1, "curve": "stepped" },
					{ "time": 0.6666, "x": 1, "y": 1, "curve": "stepped" },
					{ "time": 0.7666, "x": 1, "y": 1, "curve": "stepped" },
					{ "time": 1.0333, "x": 1, "y": 1, "curve": "stepped" },
					{ "time": 1.3, "x": 1, "y": 1 }
				]
			},
			"bone12": {
				"rotate": [
					{
						"time": 0,
						"angle": 0,
						"curve": [ 0.25, 0, 0.75, 1 ]
					},
					{
						"time": 0.2,
						"angle": 60.05,
						"curve": [ 0.25, 0, 0.75, 1 ]
					},
					{
						"time": 0.6666,
						"angle": 127.46,
						"curve": [ 0.264, 0, 0.617, 0.42 ]
					},
					{
						"time": 0.7,
						"angle": 117.3,
						"curve": [ 0.325, 0.3, 0.674, 0.69 ]
					},
					{
						"time": 0.7333,
						"angle": 1.98,
						"curve": [ 0.382, 0.57, 0.735, 1 ]
					},
					{
						"time": 0.7666,
						"angle": 322.8,
						"curve": [ 0.25, 0, 0.75, 1 ]
					},
					{
						"time": 1.0333,
						"angle": -26.36,
						"curve": [ 0.25, 0, 0.75, 1 ]
					},
					{ "time": 1.3, "angle": 0 }
				],
				"translate": [
					{
						"time": 0,
						"x": 0,
						"y": 0,
						"curve": [ 0.25, 0, 0.75, 1 ]
					},
					{ "time": 0.2, "x": 41.27, "y": -53.5, "curve": "stepped" },
					{
						"time": 0.6666,
						"x": 41.27,
						"y": -53.5,
						"curve": [ 0.264, 0, 0.617, 0.42 ]
					},
					{
						"time": 0.7,
						"x": 92.04,
						"y": -46.5,
						"curve": [ 0.325, 0.3, 0.674, 0.69 ]
					},
					{
						"time": 0.7333,
						"x": 9.33,
						"y": -68.33,
						"curve": [ 0.382, 0.57, 0.735, 1 ]
					},
					{ "time": 0.7666, "x": 0, "y": 0, "curve": "stepped" },
					{ "time": 1.3, "x": 0, "y": 0 }
				],
				"scale": [
					{
						"time": 0,
						"x": 1,
						"y": 1,
						"curve": [ 0.25, 0, 0.75, 1 ]
					},
					{
						"time": 0.2,
						"x": 1.126,
						"y": 1.126,
						"curve": [ 0.25, 0, 0.75, 1 ]
					},
					{
						"time": 0.6666,
						"x": 1.702,
						"y": 1.702,
						"curve": [ 0.25, 0, 0.75, 1 ]
					},
					{ "time": 0.7666, "x": 1, "y": 1, "curve": "stepped" },
					{ "time": 1.3, "x": 1, "y": 1 }
				]
			},
			"bone2": {
				"rotate": [
					{
						"time": 0,
						"angle": 0,
						"curve": [ 0.25, 0, 0.75, 1 ]
					},
					{
						"time": 0.2,
						"angle": -20.74,
						"curve": [ 0.25, 0, 0.75, 1 ]
					},
					{
						"time": 0.6666,
						"angle": -33.71,
						"curve": [ 0.25, 0, 0.75, 1 ]
					},
					{
						"time": 0.7333,
						"angle": 20.05,
						"curve": [ 0.25, 0, 0.75, 1 ]
					},
					{
						"time": 0.7666,
						"angle": 1.39,
						"curve": [ 0.25, 0, 0.75, 1 ]
					},
					{
						"time": 0.8666,
						"angle": -11.67,
						"curve": [ 0.25, 0, 0.75, 1 ]
					},
					{
						"time": 0.9666,
						"angle": -1.05,
						"curve": [ 0.25, 0, 0.75, 1 ]
					},
					{ "time": 1.3, "angle": 0 }
				],
				"translate": [
					{ "time": 0, "x": 0, "y": 0, "curve": "stepped" },
					{
						"time": 0.2,
						"x": 0,
						"y": 0,
						"curve": [ 0.25, 0, 0.75, 1 ]
					},
					{
						"time": 0.6666,
						"x": 1.23,
						"y": -16.76,
						"curve": [ 0.25, 0, 0.75, 1 ]
					},
					{ "time": 0.7666, "x": 0, "y": 0, "curve": "stepped" },
					{ "time": 1.3, "x": 0, "y": 0 }
				],
				"scale": [
					{ "time": 0, "x": 1, "y": 1, "curve": "stepped" },
					{ "time": 0.2, "x": 1, "y": 1, "curve": "stepped" },
					{ "time": 0.6666, "x": 1, "y": 1, "curve": "stepped" },
					{ "time": 0.7666, "x": 1, "y": 1, "curve": "stepped" },
					{ "time": 1.3, "x": 1, "y": 1 }
				]
			},
			"bone22": {
				"rotate": [
					{
						"time": 0,
						"angle": 0,
						"curve": [ 0.25, 0, 0.75, 1 ]
					},
					{
						"time": 0.2,
						"angle": 102.35,
						"curve": [ 0.25, 0, 0.75, 1 ]
					},
					{
						"time": 0.6666,
						"angle": 116.91,
						"curve": [ 0.264, 0, 0.617, 0.42 ]
					},
					{
						"time": 0.7,
						"angle": 161.5,
						"curve": [ 0.325, 0.3, 0.674, 0.69 ]
					},
					{
						"time": 0.7333,
						"angle": -10.69,
						"curve": [ 0.382, 0.57, 0.735, 1 ]
					},
					{
						"time": 0.7666,
						"angle": -13.98,
						"curve": [ 0.25, 0, 0.75, 1 ]
					},
					{
						"time": 1.0333,
						"angle": 340.31,
						"curve": [ 0.25, 0, 0.75, 1 ]
					},
					{ "time": 1.3, "angle": 0 }
				],
				"translate": [
					{
						"time": 0,
						"x": 0,
						"y": 0,
						"curve": [ 0.25, 0, 0.75, 1 ]
					},
					{
						"time": 0.2,
						"x": 119.82,
						"y": -164.94,
						"curve": [ 0.25, 0, 0.75, 1 ]
					},
					{
						"time": 0.6666,
						"x": 127.33,
						"y": -138.22,
						"curve": [ 0.264, 0, 0.617, 0.42 ]
					},
					{
						"time": 0.7,
						"x": 159.32,
						"y": -134.48,
						"curve": [ 0.325, 0.3, 0.674, 0.69 ]
					},
					{
						"time": 0.7333,
						"x": -1.78,
						"y": -128.28,
						"curve": [ 0.382, 0.57, 0.735, 1 ]
					},
					{ "time": 0.7666, "x": 0, "y": 0, "curve": "stepped" },
					{ "time": 1.3, "x": 0, "y": 0 }
				],
				"scale": [
					{ "time": 0, "x": 1, "y": 1, "curve": "stepped" },
					{
						"time": 0.2,
						"x": 1,
						"y": 1,
						"curve": [ 0.25, 0, 0.75, 1 ]
					},
					{
						"time": 0.6666,
						"x": 1.653,
						"y": 1.653,
						"curve": [ 0.25, 0, 0.75, 1 ]
					},
					{ "time": 0.7666, "x": 1, "y": 1, "curve": "stepped" },
					{ "time": 1.3, "x": 1, "y": 1 }
				]
			},
			"bone3": {
				"rotate": [
					{ "time": 0, "angle": 0, "curve": "stepped" },
					{ "time": 0.2, "angle": 0, "curve": "stepped" },
					{ "time": 0.6666, "angle": 0, "curve": "stepped" },
					{ "time": 0.7666, "angle": 0, "curve": "stepped" },
					{ "time": 1.3, "angle": 0 }
				],
				"translate": [
					{ "time": 0, "x": 0, "y": 0, "curve": "stepped" },
					{ "time": 0.2, "x": 0, "y": 0, "curve": "stepped" },
					{ "time": 0.6666, "x": 0, "y": 0, "curve": "stepped" },
					{ "time": 0.7666, "x": 0, "y": 0, "curve": "stepped" },
					{ "time": 1.3, "x": 0, "y": 0 }
				],
				"scale": [
					{ "time": 0, "x": 1, "y": 1, "curve": "stepped" },
					{ "time": 0.2, "x": 1, "y": 1, "curve": "stepped" },
					{ "time": 0.6666, "x": 1, "y": 1, "curve": "stepped" },
					{ "time": 0.7666, "x": 1, "y": 1, "curve": "stepped" },
					{ "time": 1.3, "x": 1, "y": 1 }
				]
			},
			"bone8": {
				"rotate": [
					{ "time": 0, "angle": 0, "curve": "stepped" },
					{
						"time": 0.2,
						"angle": 0,
						"curve": [ 0.25, 0, 0.75, 1 ]
					},
					{
						"time": 0.6666,
						"angle": -53.75,
						"curve": [ 0.25, 0, 0.75, 1 ]
					},
					{
						"time": 0.7666,
						"angle": 38.86,
						"curve": [ 0.25, 0, 0.75, 1 ]
					},
					{
						"time": 1.0333,
						"angle": 37.74,
						"curve": [ 0.25, 0, 0.75, 1 ]
					},
					{ "time": 1.3, "angle": 0 }
				],
				"translate": [
					{ "time": 0, "x": 0, "y": 0, "curve": "stepped" },
					{ "time": 0.2, "x": 0, "y": 0, "curve": "stepped" },
					{ "time": 0.6666, "x": 0, "y": 0, "curve": "stepped" },
					{ "time": 0.7666, "x": 0, "y": 0, "curve": "stepped" },
					{ "time": 1.3, "x": 0, "y": 0 }
				],
				"scale": [
					{ "time": 0, "x": 1, "y": 1, "curve": "stepped" },
					{ "time": 0.2, "x": 1, "y": 1, "curve": "stepped" },
					{ "time": 0.6666, "x": 1, "y": 1, "curve": "stepped" },
					{ "time": 0.7666, "x": 1, "y": 1, "curve": "stepped" },
					{ "time": 1.3, "x": 1, "y": 1 }
				]
			},
			"bone9": {
				"rotate": [
					{
						"time": 0,
						"angle": 0,
						"curve": [ 0.25, 0, 0.75, 1 ]
					},
					{
						"time": 0.2,
						"angle": 18.75,
						"curve": [ 0.25, 0, 0.75, 1 ]
					},
					{
						"time": 0.7,
						"angle": -12.07,
						"curve": [ 0.25, 0, 0.75, 1 ]
					},
					{
						"time": 0.9333,
						"angle": 16.06,
						"curve": [ 0.25, 0, 0.75, 1 ]
					},
					{ "time": 1.3, "angle": 0 }
				],
				"translate": [
					{ "time": 0, "x": 0, "y": 0, "curve": "stepped" },
					{ "time": 1.3, "x": 0, "y": 0 }
				],
				"scale": [
					{ "time": 0, "x": 1, "y": 1, "curve": "stepped" },
					{ "time": 1.3, "x": 1, "y": 1 }
				]
			},
			"bone10": {
				"rotate": [
					{
						"time": 0,
						"angle": 0,
						"curve": [ 0.25, 0, 0.75, 1 ]
					},
					{
						"time": 0.1333,
						"angle": -43.31,
						"curve": [ 0.25, 0, 0.75, 1 ]
					},
					{
						"time": 0.4333,
						"angle": 27.9,
						"curve": [ 0.25, 0, 0.75, 1 ]
					},
					{
						"time": 0.8666,
						"angle": -50.62,
						"curve": [ 0.25, 0, 0.75, 1 ]
					},
					{ "time": 1.3, "angle": 0 }
				],
				"translate": [
					{ "time": 0, "x": 0, "y": 0, "curve": "stepped" },
					{ "time": 1.3, "x": 0, "y": 0 }
				],
				"scale": [
					{ "time": 0, "x": 1, "y": 1, "curve": "stepped" },
					{ "time": 1.3, "x": 1, "y": 1 }
				]
			},
			"bone13": {
				"rotate": [
					{
						"time": 0,
						"angle": 0,
						"curve": [ 0.25, 0, 0.75, 1 ]
					},
					{
						"time": 0.2,
						"angle": -47.37,
						"curve": [ 0.25, 0, 0.75, 1 ]
					},
					{
						"time": 0.6666,
						"angle": -14.01,
						"curve": [ 0.25, 0, 0.75, 1 ]
					},
					{
						"time": 0.7666,
						"angle": 57.08,
						"curve": [ 0.25, 0, 0.75, 1 ]
					},
					{ "time": 1.3, "angle": 0 }
				],
				"translate": [
					{
						"time": 0,
						"x": 0,
						"y": 0,
						"curve": [ 0.25, 0, 0.75, 1 ]
					},
					{ "time": 0.2, "x": 11.77, "y": -0.87, "curve": "stepped" },
					{
						"time": 0.6666,
						"x": 11.77,
						"y": -0.87,
						"curve": [ 0.25, 0, 0.75, 1 ]
					},
					{ "time": 0.7666, "x": 0, "y": 0, "curve": "stepped" },
					{ "time": 1.3, "x": 0, "y": 0 }
				],
				"scale": [
					{ "time": 0, "x": 1, "y": 1, "curve": "stepped" },
					{ "time": 0.2, "x": 1, "y": 1, "curve": "stepped" },
					{ "time": 0.6666, "x": 1, "y": 1, "curve": "stepped" },
					{ "time": 0.7666, "x": 1, "y": 1, "curve": "stepped" },
					{ "time": 1.3, "x": 1, "y": 1 }
				]
			},
			"bone14": {
				"rotate": [
					{
						"time": 0,
						"angle": 0,
						"curve": [ 0.25, 0, 0.75, 1 ]
					},
					{
						"time": 0.2,
						"angle": -49.8,
						"curve": [ 0.25, 0, 0.75, 1 ]
					},
					{
						"time": 0.6666,
						"angle": 20.33,
						"curve": [ 0.25, 0, 0.75, 1 ]
					},
					{
						"time": 0.7666,
						"angle": -57.24,
						"curve": [ 0.25, 0, 0.75, 1 ]
					},
					{ "time": 1.3, "angle": 0 }
				],
				"translate": [
					{
						"time": 0,
						"x": 0,
						"y": 0,
						"curve": [ 0.25, 0, 0.75, 1 ]
					},
					{ "time": 0.2, "x": 3.65, "y": 12.47, "curve": "stepped" },
					{
						"time": 0.6666,
						"x": 3.65,
						"y": 12.47,
						"curve": [ 0.25, 0, 0.75, 1 ]
					},
					{ "time": 0.7666, "x": 0, "y": 0, "curve": "stepped" },
					{ "time": 1.3, "x": 0, "y": 0 }
				],
				"scale": [
					{ "time": 0, "x": 1, "y": 1, "curve": "stepped" },
					{ "time": 0.2, "x": 1, "y": 1, "curve": "stepped" },
					{ "time": 0.6666, "x": 1, "y": 1, "curve": "stepped" },
					{ "time": 0.7666, "x": 1, "y": 1, "curve": "stepped" },
					{ "time": 1.3, "x": 1, "y": 1 }
				]
			},
			"bone15": {
				"rotate": [
					{
						"time": 0,
						"angle": 0,
						"curve": [ 0.25, 0, 0.75, 1 ]
					},
					{
						"time": 0.2,
						"angle": -14.99,
						"curve": [ 0.25, 0, 0.75, 1 ]
					},
					{
						"time": 0.6666,
						"angle": -21.42,
						"curve": [ 0.25, 0, 0.75, 1 ]
					},
					{
						"time": 0.9333,
						"angle": 8.27,
						"curve": [ 0.25, 0, 0.75, 1 ]
					},
					{ "time": 1.3, "angle": 0 }
				],
				"translate": [
					{ "time": 0, "x": 0, "y": 0, "curve": "stepped" },
					{ "time": 1.3, "x": 0, "y": 0 }
				],
				"scale": [
					{ "time": 0, "x": 1, "y": 1, "curve": "stepped" },
					{ "time": 1.3, "x": 1, "y": 1 }
				]
			},
			"bone17": {
				"rotate": [
					{
						"time": 0,
						"angle": 0,
						"curve": [ 0.25, 0, 0.75, 1 ]
					},
					{
						"time": 0.2,
						"angle": -37.64,
						"curve": [ 0.25, 0, 0.75, 1 ]
					},
					{
						"time": 0.7,
						"angle": -307.45,
						"curve": [ 0.25, 0, 0.75, 1 ]
					},
					{
						"time": 0.8333,
						"angle": -313.9,
						"curve": [ 0.25, 0, 0.75, 1 ]
					},
					{ "time": 1.3, "angle": 0 }
				],
				"translate": [
					{ "time": 0, "x": 0, "y": 0, "curve": "stepped" },
					{ "time": 1.3, "x": 0, "y": 0 }
				],
				"scale": [
					{ "time": 0, "x": 1, "y": 1, "curve": "stepped" },
					{ "time": 1.3, "x": 1, "y": 1 }
				]
			},
			"bone18": {
				"rotate": [
					{
						"time": 0,
						"angle": 0,
						"curve": [ 0.25, 0, 0.75, 1 ]
					},
					{
						"time": 0.3,
						"angle": 26.09,
						"curve": [ 0.25, 0, 0.75, 1 ]
					},
					{
						"time": 0.8333,
						"angle": -20.86,
						"curve": [ 0.25, 0, 0.75, 1 ]
					},
					{ "time": 1.3, "angle": 0 }
				],
				"translate": [
					{ "time": 0, "x": 0, "y": 0, "curve": "stepped" },
					{ "time": 1.3, "x": 0, "y": 0 }
				],
				"scale": [
					{ "time": 0, "x": 1, "y": 1, "curve": "stepped" },
					{ "time": 1.3, "x": 1, "y": 1 }
				]
			},
			"bone19": {
				"rotate": [
					{
						"time": 0,
						"angle": 0,
						"curve": [ 0.25, 0, 0.75, 1 ]
					},
					{
						"time": 0.2666,
						"angle": 35.03,
						"curve": [ 0.25, 0, 0.75, 1 ]
					},
					{
						"time": 0.7666,
						"angle": -14.4,
						"curve": [ 0.25, 0, 0.75, 1 ]
					},
					{
						"time": 1.0333,
						"angle": -1.24,
						"curve": [ 0.25, 0, 0.75, 1 ]
					},
					{ "time": 1.3, "angle": 0 }
				],
				"translate": [
					{ "time": 0, "x": 0, "y": 0, "curve": "stepped" },
					{ "time": 1.3, "x": 0, "y": 0 }
				],
				"scale": [
					{ "time": 0, "x": 1, "y": 1, "curve": "stepped" },
					{ "time": 1.3, "x": 1, "y": 1 }
				]
			},
			"bone21": {
				"rotate": [
					{
						"time": 0,
						"angle": 0,
						"curve": [ 0.25, 0, 0.75, 1 ]
					},
					{
						"time": 0.3333,
						"angle": -17.01,
						"curve": [ 0.25, 0, 0.75, 1 ]
					},
					{
						"time": 0.8333,
						"angle": 32.26,
						"curve": [ 0.25, 0, 0.75, 1 ]
					},
					{
						"time": 1.1,
						"angle": -17.26,
						"curve": [ 0.25, 0, 0.75, 1 ]
					},
					{ "time": 1.3, "angle": 0 }
				],
				"translate": [
					{ "time": 0, "x": 0, "y": 0, "curve": "stepped" },
					{ "time": 1.3, "x": 0, "y": 0 }
				],
				"scale": [
					{ "time": 0, "x": 1, "y": 1, "curve": "stepped" },
					{ "time": 1.3, "x": 1, "y": 1 }
				]
			},
			"bone23": {
				"rotate": [
					{
						"time": 0,
						"angle": 0,
						"curve": [ 0.25, 0, 0.75, 1 ]
					},
					{
						"time": 0.2,
						"angle": 25.7,
						"curve": [ 0.25, 0, 0.75, 1 ]
					},
					{
						"time": 0.6666,
						"angle": -34.29,
						"curve": [ 0.25, 0, 0.75, 1 ]
					},
					{ "time": 0.7666, "angle": 0, "curve": "stepped" },
					{ "time": 1.3, "angle": 0 }
				],
				"translate": [
					{
						"time": 0,
						"x": 0,
						"y": 0,
						"curve": [ 0.25, 0, 0.75, 1 ]
					},
					{ "time": 0.2, "x": 4.04, "y": -8.51, "curve": "stepped" },
					{
						"time": 0.6666,
						"x": 4.04,
						"y": -8.51,
						"curve": [ 0.25, 0, 0.75, 1 ]
					},
					{ "time": 0.7666, "x": 0, "y": 0, "curve": "stepped" },
					{ "time": 1.3, "x": 0, "y": 0 }
				],
				"scale": [
					{ "time": 0, "x": 1, "y": 1, "curve": "stepped" },
					{ "time": 0.2, "x": 1, "y": 1, "curve": "stepped" },
					{ "time": 0.6666, "x": 1, "y": 1, "curve": "stepped" },
					{ "time": 0.7666, "x": 1, "y": 1, "curve": "stepped" },
					{ "time": 1.3, "x": 1, "y": 1 }
				]
			},
			"bone24": {
				"rotate": [
					{
						"time": 0,
						"angle": 0,
						"curve": [ 0.25, 0, 0.75, 1 ]
					},
					{
						"time": 0.2,
						"angle": -73.79,
						"curve": [ 0.25, 0, 0.75, 1 ]
					},
					{
						"time": 0.6666,
						"angle": 31.67,
						"curve": [ 0.25, 0, 0.75, 1 ]
					},
					{ "time": 0.7666, "angle": 0, "curve": "stepped" },
					{ "time": 1.3, "angle": 0 }
				],
				"translate": [
					{
						"time": 0,
						"x": 0,
						"y": 0,
						"curve": [ 0.25, 0, 0.75, 1 ]
					},
					{ "time": 0.2, "x": 5.18, "y": 11.31, "curve": "stepped" },
					{
						"time": 0.6666,
						"x": 5.18,
						"y": 11.31,
						"curve": [ 0.25, 0, 0.75, 1 ]
					},
					{ "time": 0.7666, "x": 0, "y": 0, "curve": "stepped" },
					{ "time": 1.3, "x": 0, "y": 0 }
				],
				"scale": [
					{ "time": 0, "x": 1, "y": 1, "curve": "stepped" },
					{ "time": 0.2, "x": 1, "y": 1, "curve": "stepped" },
					{ "time": 0.6666, "x": 1, "y": 1, "curve": "stepped" },
					{ "time": 0.7666, "x": 1, "y": 1, "curve": "stepped" },
					{ "time": 1.3, "x": 1, "y": 1 }
				]
			},
			"bone4": {
				"rotate": [
					{
						"time": 0,
						"angle": 0,
						"curve": [ 0.25, 0, 0.75, 1 ]
					},
					{
						"time": 0.2,
						"angle": -66.14,
						"curve": [ 0.25, 0, 0.75, 1 ]
					},
					{
						"time": 0.6666,
						"angle": 42.07,
						"curve": [ 0.25, 0, 0.75, 1 ]
					},
					{
						"time": 0.7666,
						"angle": -29.77,
						"curve": [ 0.25, 0, 0.75, 1 ]
					},
					{
						"time": 1.0333,
						"angle": -27.92,
						"curve": [ 0.25, 0, 0.75, 1 ]
					},
					{ "time": 1.3, "angle": 0 }
				],
				"translate": [
					{ "time": 0, "x": 0, "y": 0, "curve": "stepped" },
					{ "time": 0.2, "x": 0, "y": 0, "curve": "stepped" },
					{ "time": 0.6666, "x": 0, "y": 0, "curve": "stepped" },
					{ "time": 0.7666, "x": 0, "y": 0, "curve": "stepped" },
					{ "time": 1.3, "x": 0, "y": 0 }
				],
				"scale": [
					{ "time": 0, "x": 1, "y": 1, "curve": "stepped" },
					{ "time": 0.2, "x": 1, "y": 1, "curve": "stepped" },
					{ "time": 0.6666, "x": 1, "y": 1, "curve": "stepped" },
					{ "time": 0.7666, "x": 1, "y": 1, "curve": "stepped" },
					{ "time": 1.3, "x": 1, "y": 1 }
				]
			},
			"bone11": {
				"rotate": [
					{
						"time": 0,
						"angle": 0,
						"curve": [ 0.25, 0, 0.75, 1 ]
					},
					{
						"time": 0.2,
						"angle": -39.62,
						"curve": [ 0.25, 0, 0.75, 1 ]
					},
					{
						"time": 0.7,
						"angle": 24.45,
						"curve": [ 0.25, 0, 0.75, 1 ]
					},
					{
						"time": 0.9333,
						"angle": -30.72,
						"curve": [ 0.25, 0, 0.75, 1 ]
					},
					{ "time": 1.3, "angle": 0 }
				],
				"translate": [
					{ "time": 0, "x": 0, "y": 0, "curve": "stepped" },
					{ "time": 1.3, "x": 0, "y": 0 }
				],
				"scale": [
					{ "time": 0, "x": 1, "y": 1, "curve": "stepped" },
					{ "time": 1.3, "x": 1, "y": 1 }
				]
			},
			"bone16": {
				"rotate": [
					{
						"time": 0,
						"angle": 0,
						"curve": [ 0.25, 0, 0.75, 1 ]
					},
					{
						"time": 0.1333,
						"angle": 43.56,
						"curve": [ 0.25, 0, 0.75, 1 ]
					},
					{
						"time": 0.4,
						"angle": -34.22,
						"curve": [ 0.25, 0, 0.75, 1 ]
					},
					{
						"time": 0.9333,
						"angle": 42.26,
						"curve": [ 0.25, 0, 0.75, 1 ]
					},
					{ "time": 1.3, "angle": 0 }
				],
				"translate": [
					{ "time": 0, "x": 0, "y": 0, "curve": "stepped" },
					{ "time": 1.3, "x": 0, "y": 0 }
				],
				"scale": [
					{ "time": 0, "x": 1, "y": 1, "curve": "stepped" },
					{ "time": 1.3, "x": 1, "y": 1 }
				]
			},
			"bone20": {
				"rotate": [
					{
						"time": 0,
						"angle": 0,
						"curve": [ 0.25, 0, 0.75, 1 ]
					},
					{
						"time": 0.2,
						"angle": -39.94,
						"curve": [ 0.25, 0, 0.75, 1 ]
					},
					{
						"time": 0.7,
						"angle": 85.79,
						"curve": [ 0.25, 0, 0.75, 1 ]
					},
					{
						"time": 1.0333,
						"angle": -20.2,
						"curve": [ 0.25, 0, 0.75, 1 ]
					},
					{ "time": 1.3, "angle": 0 }
				],
				"translate": [
					{ "time": 0, "x": 0, "y": 0, "curve": "stepped" },
					{ "time": 1.3, "x": 0, "y": 0 }
				],
				"scale": [
					{ "time": 0, "x": 1, "y": 1, "curve": "stepped" },
					{ "time": 1.3, "x": 1, "y": 1 }
				]
			},
			"bone5": {
				"rotate": [
					{ "time": 0, "angle": 0, "curve": "stepped" },
					{ "time": 0.2, "angle": 0, "curve": "stepped" },
					{
						"time": 0.6666,
						"angle": 0,
						"curve": [ 0.25, 0, 0.75, 1 ]
					},
					{
						"time": 0.7666,
						"angle": 19.51,
						"curve": [ 0.25, 0, 0.75, 1 ]
					},
					{
						"time": 1.0333,
						"angle": -13.03,
						"curve": [ 0.25, 0, 0.75, 1 ]
					},
					{ "time": 1.3, "angle": 0 }
				],
				"translate": [
					{ "time": 0, "x": 0, "y": 0, "curve": "stepped" },
					{ "time": 0.2, "x": 0, "y": 0, "curve": "stepped" },
					{ "time": 0.6666, "x": 0, "y": 0, "curve": "stepped" },
					{ "time": 0.7666, "x": 0, "y": 0, "curve": "stepped" },
					{ "time": 1.3, "x": 0, "y": 0 }
				],
				"scale": [
					{ "time": 0, "x": 1, "y": 1, "curve": "stepped" },
					{ "time": 0.2, "x": 1, "y": 1, "curve": "stepped" },
					{ "time": 0.6666, "x": 1, "y": 1, "curve": "stepped" },
					{ "time": 0.7666, "x": 1, "y": 1, "curve": "stepped" },
					{ "time": 1.3, "x": 1, "y": 1 }
				]
			},
			"bone7": {
				"rotate": [
					{ "time": 0, "angle": 0, "curve": "stepped" },
					{ "time": 0.2, "angle": 0, "curve": "stepped" },
					{ "time": 0.6666, "angle": 0, "curve": "stepped" },
					{ "time": 0.7666, "angle": 0, "curve": "stepped" },
					{ "time": 1.3, "angle": 0 }
				],
				"translate": [
					{ "time": 0, "x": 0, "y": 0, "curve": "stepped" },
					{ "time": 0.2, "x": 0, "y": 0, "curve": "stepped" },
					{ "time": 0.6666, "x": 0, "y": 0, "curve": "stepped" },
					{ "time": 0.7666, "x": 0, "y": 0, "curve": "stepped" },
					{ "time": 1.3, "x": 0, "y": 0 }
				],
				"scale": [
					{ "time": 0, "x": 1, "y": 1, "curve": "stepped" },
					{ "time": 0.2, "x": 1, "y": 1, "curve": "stepped" },
					{ "time": 0.6666, "x": 1, "y": 1, "curve": "stepped" },
					{ "time": 0.7666, "x": 1, "y": 1, "curve": "stepped" },
					{ "time": 1.3, "x": 1, "y": 1 }
				]
			},
			"bone6": {
				"rotate": [
					{ "time": 0, "angle": 0, "curve": "stepped" },
					{ "time": 0.2, "angle": 0, "curve": "stepped" },
					{
						"time": 0.6666,
						"angle": 0,
						"curve": [ 0.25, 0, 0.75, 1 ]
					},
					{
						"time": 0.7666,
						"angle": 32,
						"curve": [ 0.25, 0, 0.75, 1 ]
					},
					{
						"time": 1.0333,
						"angle": -24.66,
						"curve": [ 0.25, 0, 0.75, 1 ]
					},
					{ "time": 1.3, "angle": 0 }
				],
				"translate": [
					{ "time": 0, "x": 0, "y": 0, "curve": "stepped" },
					{ "time": 0.2, "x": 0, "y": 0, "curve": "stepped" },
					{ "time": 0.6666, "x": 0, "y": 0, "curve": "stepped" },
					{ "time": 0.7666, "x": 0, "y": 0, "curve": "stepped" },
					{ "time": 1.3, "x": 0, "y": 0 }
				],
				"scale": [
					{ "time": 0, "x": 1, "y": 1, "curve": "stepped" },
					{ "time": 0.2, "x": 1, "y": 1, "curve": "stepped" },
					{ "time": 0.6666, "x": 1, "y": 1, "curve": "stepped" },
					{ "time": 0.7666, "x": 1, "y": 1, "curve": "stepped" },
					{ "time": 1.3, "x": 1, "y": 1 }
				]
			},
			"bone28": {
				"translate": [
					{ "time": 0.7, "x": 1059.13, "y": -330.12 }
				],
				"scale": [
					{ "time": 0.7, "x": 2.5, "y": 2.5 }
				]
			}
		},
		"ffd": {
			"default": {
				"chibang12": {
					"chibang1": [
						{
							"time": 0,
							"curve": [ 0.25, 0, 0.75, 1 ]
						},
						{
							"time": 0.2,
							"offset": 58,
							"vertices": [ 16.21, -2.46, -4.21, 15.84, -3.47, 16.02, 0.89, 16.37, 25.99, -15.65, 3.97, 30.08, 13.08, 27.37, -14.21, -3.43, 0, 0, 0, 0, 0, 0, -2.86, -5.43, 0, 0, 0, 0, 0, 0, 0, 0, 9.74, 6.99, -10.3, 6.13, -10, 6.6, -7.9, 9.02, -9.68, 42.78, 0, 0, 0, 0, 0, 0, 0, 0, 0, 0, 0, 0, 0, 0, 0, 0, 0, 0, 0, 0, 0, 0, 15.93, -8.38, 17.47, 4.3, 1.32, 17.95, 2.15, 17.86, 6.8, 16.66 ],
							"curve": [ 0.25, 0, 0.75, 1 ]
						},
						{ "time": 0.6666, "curve": "stepped" },
						{ "time": 1.3 }
					]
				},
				"daizi12": {
					"daizi1": [
						{ "time": 0 }
					]
				},
				"daizi22": {
					"daizi2": [
						{ "time": 0 }
					]
				},
				"jiao12": {
					"jiao1": [
						{ "time": 0 }
					]
				},
				"jiao22": {
					"jiao2": [
						{ "time": 0 }
					]
				},
				"shenti2": {
					"shenti": [
						{ "time": 0 }
					]
				},
				"weiba2": {
					"weiba": [
						{ "time": 0 }
					]
				},
				"yumao2": {
					"yumao2": [
						{ "time": 0 }
					]
				},
				"yumao12": {
					"yumao1": [
						{ "time": 0 }
					]
				},
				"yumao32": {
					"yumao3": [
						{ "time": 0 }
					]
				}
			}
		},
		"drawOrder": [
			{ "time": 0 },
			{
				"time": 0.7,
				"offsets": [
					{ "slot": "jineng/zhuaji019", "offset": -13 }
				]
			}
		],
		"events": [
			{ "time": 1.2666, "name": "callback", "int": 1 }
		]
	},
	"load": {
		"slots": {
			"chibang12": {
				"attachment": [
					{ "time": 0, "name": "chibang1" }
				]
			},
			"chibang22": {
				"attachment": [
					{ "time": 0, "name": "chibang2" }
				]
			},
			"daizi12": {
				"attachment": [
					{ "time": 0, "name": "daizi1" }
				]
			},
			"daizi22": {
				"attachment": [
					{ "time": 0, "name": "daizi2" }
				]
			},
			"gongji/qiangkou/qiangkou018": {
				"attachment": [
					{ "time": 0, "name": null }
				]
			},
			"gongji/qiangkou/qiangkou0182": {
				"attachment": [
					{ "time": 0, "name": null }
				]
			},
			"jiao12": {
				"attachment": [
					{ "time": 0, "name": "jiao1" }
				]
			},
			"jiao22": {
				"attachment": [
					{ "time": 0, "name": "jiao2" }
				]
			},
			"jineng/zhuaji019": {
				"attachment": [
					{ "time": 0, "name": null }
				]
			},
			"shenti2": {
				"attachment": [
					{ "time": 0, "name": "shenti" }
				]
			},
			"weiba2": {
				"attachment": [
					{ "time": 0, "name": "weiba" }
				]
			},
			"yumao2": {
				"attachment": [
					{ "time": 0, "name": "yumao2" }
				]
			},
			"yumao12": {
				"attachment": [
					{ "time": 0, "name": "yumao1" }
				]
			},
			"yumao32": {
				"attachment": [
					{ "time": 0, "name": "yumao3" }
				]
			}
		},
		"bones": {
			"root": {
				"rotate": [
					{ "time": 0, "angle": 0, "curve": "stepped" },
					{ "time": 1, "angle": 0 }
				],
				"translate": [
					{ "time": 0, "x": 0, "y": 0, "curve": "stepped" },
					{ "time": 1, "x": 0, "y": 0 }
				],
				"scale": [
					{ "time": 0, "x": 0.999, "y": 0.999, "curve": "stepped" },
					{ "time": 1, "x": 0.999, "y": 0.999 }
				]
			},
			"bone": {
				"rotate": [
					{ "time": 0, "angle": 0, "curve": "stepped" },
					{ "time": 1, "angle": 0 }
				],
				"translate": [
					{
						"time": 0,
						"x": 0,
						"y": 0,
						"curve": [ 0.25, 0, 0.75, 1 ]
					},
					{
						"time": 0.5,
						"x": 0,
						"y": -30.11,
						"curve": [ 0.25, 0, 0.75, 1 ]
					},
					{ "time": 1, "x": 0, "y": 0 }
				],
				"scale": [
					{ "time": 0, "x": 1, "y": 1, "curve": "stepped" },
					{ "time": 1, "x": 1, "y": 1 }
				]
			},
			"bone12": {
				"rotate": [
					{
						"time": 0,
						"angle": 0,
						"curve": [ 0.25, 0, 0.75, 1 ]
					},
					{
						"time": 0.5,
						"angle": -7.56,
						"curve": [ 0.25, 0, 0.75, 1 ]
					},
					{ "time": 1, "angle": 0 }
				],
				"translate": [
					{ "time": 0, "x": 0, "y": 0, "curve": "stepped" },
					{ "time": 1, "x": 0, "y": 0 }
				],
				"scale": [
					{ "time": 0, "x": 1, "y": 1, "curve": "stepped" },
					{ "time": 1, "x": 1, "y": 1 }
				]
			},
			"bone2": {
				"rotate": [
					{
						"time": 0,
						"angle": 0,
						"curve": [ 0.198, 0.28, 0.75, 1 ]
					},
					{
						"time": 0.3,
						"angle": 2.46,
						"curve": [ 0.25, 0, 0.75, 1 ]
					},
					{
						"time": 0.8,
						"angle": -1.37,
						"curve": [ 0.25, 0, 0.804, 0.73 ]
					},
					{ "time": 1, "angle": 0 }
				],
				"translate": [
					{ "time": 0, "x": 0, "y": 0, "curve": "stepped" },
					{ "time": 1, "x": 0, "y": 0 }
				],
				"scale": [
					{ "time": 0, "x": 1, "y": 1, "curve": "stepped" },
					{ "time": 1, "x": 1, "y": 1 }
				]
			},
			"bone22": {
				"rotate": [
					{ "time": 0, "angle": 0, "curve": "stepped" },
					{ "time": 1, "angle": 0 }
				],
				"translate": [
					{ "time": 0, "x": 0, "y": 0, "curve": "stepped" },
					{ "time": 1, "x": 0, "y": 0 }
				],
				"scale": [
					{ "time": 0, "x": 1, "y": 1, "curve": "stepped" },
					{ "time": 1, "x": 1, "y": 1 }
				]
			},
			"bone3": {
				"rotate": [
					{ "time": 0, "angle": 0, "curve": "stepped" },
					{ "time": 1, "angle": 0 }
				],
				"translate": [
					{ "time": 0, "x": 0, "y": 0, "curve": "stepped" },
					{ "time": 1, "x": 0, "y": 0 }
				],
				"scale": [
					{ "time": 0, "x": 1, "y": 1, "curve": "stepped" },
					{ "time": 1, "x": 1, "y": 1 }
				]
			},
			"bone8": {
				"rotate": [
					{
						"time": 0,
						"angle": 0,
						"curve": [ 0.201, 0.27, 0.75, 1 ]
					},
					{
						"time": 0.3,
						"angle": -8.84,
						"curve": [ 0.25, 0, 0.75, 1 ]
					},
					{
						"time": 0.7333,
						"angle": 5.28,
						"curve": [ 0.25, 0, 0.775, 0.71 ]
					},
					{ "time": 1, "angle": 0 }
				],
				"translate": [
					{ "time": 0, "x": 0, "y": 0, "curve": "stepped" },
					{ "time": 1, "x": 0, "y": 0 }
				],
				"scale": [
					{ "time": 0, "x": 1, "y": 1, "curve": "stepped" },
					{ "time": 1, "x": 1, "y": 1 }
				]
			},
			"bone9": {
				"rotate": [
					{
						"time": 0,
						"angle": 0,
						"curve": [ 0.25, 0, 0.75, 1 ]
					},
					{
						"time": 0.5,
						"angle": -8.72,
						"curve": [ 0.25, 0, 0.75, 1 ]
					},
					{ "time": 1, "angle": 0 }
				],
				"translate": [
					{
						"time": 0,
						"x": 0,
						"y": 0,
						"curve": [ 0.25, 0, 0.625, 0.5 ]
					},
					{
						"time": 0.5,
						"x": 6.21,
						"y": -0.78,
						"curve": [ 0.375, 0.5, 0.75, 1 ]
					},
					{ "time": 1, "x": 0, "y": 0 }
				],
				"scale": [
					{ "time": 0, "x": 1, "y": 1, "curve": "stepped" },
					{ "time": 1, "x": 1, "y": 1 }
				]
			},
			"bone10": {
				"rotate": [
					{
						"time": 0,
						"angle": 0,
						"curve": [ 0.224, 0.3, 0.75, 1 ]
					},
					{
						"time": 0.2666,
						"angle": 8.25,
						"curve": [ 0.25, 0, 0.75, 1 ]
					},
					{
						"time": 0.7,
						"angle": -2.73,
						"curve": [ 0.25, 0, 0.795, 0.76 ]
					},
					{ "time": 1, "angle": 0 }
				],
				"translate": [
					{
						"time": 0,
						"x": 0,
						"y": 0,
						"curve": [ 0.25, 0, 0.75, 1 ]
					},
					{
						"time": 0.5333,
						"x": -10.08,
						"y": -6.6,
						"curve": [ 0.25, 0, 0.75, 1 ]
					},
					{ "time": 1, "x": 0, "y": 0 }
				],
				"scale": [
					{ "time": 0, "x": 1, "y": 1, "curve": "stepped" },
					{ "time": 1, "x": 1, "y": 1 }
				]
			},
			"bone13": {
				"rotate": [
					{
						"time": 0,
						"angle": 0,
						"curve": [ 0.25, 0, 0.75, 1 ]
					},
					{
						"time": 0.5,
						"angle": 27.19,
						"curve": [ 0.25, 0, 0.75, 1 ]
					},
					{ "time": 1, "angle": 0 }
				],
				"translate": [
					{ "time": 0, "x": 0, "y": 0, "curve": "stepped" },
					{ "time": 1, "x": 0, "y": 0 }
				],
				"scale": [
					{ "time": 0, "x": 1, "y": 1, "curve": "stepped" },
					{ "time": 1, "x": 1, "y": 1 }
				]
			},
			"bone14": {
				"rotate": [
					{
						"time": 0,
						"angle": 0,
						"curve": [ 0.25, 0, 0.75, 1 ]
					},
					{
						"time": 0.4333,
						"angle": -21.59,
						"curve": [ 0.25, 0, 0.75, 1 ]
					},
					{ "time": 1, "angle": 0 }
				],
				"translate": [
					{ "time": 0, "x": 0, "y": 0, "curve": "stepped" },
					{ "time": 1, "x": 0, "y": 0 }
				],
				"scale": [
					{ "time": 0, "x": 1, "y": 1, "curve": "stepped" },
					{ "time": 1, "x": 1, "y": 1 }
				]
			},
			"bone15": {
				"rotate": [
					{
						"time": 0,
						"angle": 0,
						"curve": [ 0.25, 0, 0.75, 1 ]
					},
					{
						"time": 0.5333,
						"angle": 16.45,
						"curve": [ 0.25, 0, 0.75, 1 ]
					},
					{ "time": 1, "angle": 0 }
				],
				"translate": [
					{ "time": 0, "x": 0, "y": 0, "curve": "stepped" },
					{ "time": 1, "x": 0, "y": 0 }
				],
				"scale": [
					{ "time": 0, "x": 1, "y": 1, "curve": "stepped" },
					{ "time": 1, "x": 1, "y": 1 }
				]
			},
			"bone17": {
				"rotate": [
					{
						"time": 0,
						"angle": 0,
						"curve": [ 0.25, 0, 0.75, 1 ]
					},
					{
						"time": 0.4333,
						"angle": 28.52,
						"curve": [ 0.25, 0, 0.75, 1 ]
					},
					{ "time": 1, "angle": 0 }
				],
				"translate": [
					{ "time": 0, "x": 0, "y": 0, "curve": "stepped" },
					{ "time": 1, "x": 0, "y": 0 }
				],
				"scale": [
					{ "time": 0, "x": 1, "y": 1, "curve": "stepped" },
					{ "time": 1, "x": 1, "y": 1 }
				]
			},
			"bone18": {
				"rotate": [
					{
						"time": 0,
						"angle": 0,
						"curve": [ 0.25, 0, 0.75, 1 ]
					},
					{
						"time": 0.5,
						"angle": 21.71,
						"curve": [ 0.25, 0, 0.75, 1 ]
					},
					{ "time": 1, "angle": 0 }
				],
				"translate": [
					{ "time": 0, "x": 0, "y": 0, "curve": "stepped" },
					{ "time": 1, "x": 0, "y": 0 }
				],
				"scale": [
					{ "time": 0, "x": 1, "y": 1, "curve": "stepped" },
					{ "time": 1, "x": 1, "y": 1 }
				]
			},
			"bone19": {
				"rotate": [
					{
						"time": 0,
						"angle": 0,
						"curve": [ 0.25, 0, 0.75, 1 ]
					},
					{
						"time": 0.5,
						"angle": -14.33,
						"curve": [ 0.25, 0, 0.75, 1 ]
					},
					{ "time": 1, "angle": 0 }
				],
				"translate": [
					{ "time": 0, "x": 0, "y": 0, "curve": "stepped" },
					{ "time": 1, "x": 0, "y": 0 }
				],
				"scale": [
					{ "time": 0, "x": 1, "y": 1, "curve": "stepped" },
					{ "time": 1, "x": 1, "y": 1 }
				]
			},
			"bone21": {
				"rotate": [
					{
						"time": 0,
						"angle": 0,
						"curve": [ 0.25, 0, 0.75, 1 ]
					},
					{
						"time": 0.5333,
						"angle": -16.36,
						"curve": [ 0.25, 0, 0.75, 1 ]
					},
					{ "time": 1, "angle": 0 }
				],
				"translate": [
					{ "time": 0, "x": 0, "y": 0, "curve": "stepped" },
					{ "time": 1, "x": 0, "y": 0 }
				],
				"scale": [
					{ "time": 0, "x": 1, "y": 1, "curve": "stepped" },
					{ "time": 1, "x": 1, "y": 1 }
				]
			},
			"bone23": {
				"rotate": [
					{ "time": 0, "angle": 0, "curve": "stepped" },
					{ "time": 1, "angle": 0 }
				],
				"translate": [
					{ "time": 0, "x": 0, "y": 0, "curve": "stepped" },
					{ "time": 1, "x": 0, "y": 0 }
				],
				"scale": [
					{ "time": 0, "x": 1, "y": 1, "curve": "stepped" },
					{ "time": 1, "x": 1, "y": 1 }
				]
			},
			"bone24": {
				"rotate": [
					{ "time": 0, "angle": 0 },
					{ "time": 0.2666, "angle": 9.88 },
					{ "time": 0.7333, "angle": -10.92 },
					{ "time": 1, "angle": 0 }
				],
				"translate": [
					{ "time": 0, "x": 0, "y": 0, "curve": "stepped" },
					{ "time": 1, "x": 0, "y": 0 }
				],
				"scale": [
					{ "time": 0, "x": 1, "y": 1, "curve": "stepped" },
					{ "time": 1, "x": 1, "y": 1 }
				]
			},
			"bone4": {
				"rotate": [
					{
						"time": 0,
						"angle": 0,
						"curve": [ 0.212, 0.26, 0.75, 1 ]
					},
					{
						"time": 0.3,
						"angle": 12.53,
						"curve": [ 0.25, 0, 0.75, 1 ]
					},
					{
						"time": 0.7333,
						"angle": -9.08,
						"curve": [ 0.25, 0, 0.79, 0.72 ]
					},
					{ "time": 1, "angle": 0 }
				],
				"translate": [
					{ "time": 0, "x": 0, "y": 0, "curve": "stepped" },
					{ "time": 1, "x": 0, "y": 0 }
				],
				"scale": [
					{ "time": 0, "x": 1, "y": 1, "curve": "stepped" },
					{ "time": 1, "x": 1, "y": 1 }
				]
			},
			"bone11": {
				"rotate": [
					{
						"time": 0,
						"angle": 0,
						"curve": [ 0.25, 0, 0.75, 1 ]
					},
					{
						"time": 0.5,
						"angle": 16.09,
						"curve": [ 0.25, 0, 0.75, 1 ]
					},
					{ "time": 1, "angle": 0 }
				],
				"translate": [
					{ "time": 0, "x": 0, "y": 0, "curve": "stepped" },
					{ "time": 1, "x": 0, "y": 0 }
				],
				"scale": [
					{ "time": 0, "x": 1, "y": 1, "curve": "stepped" },
					{ "time": 1, "x": 1, "y": 1 }
				]
			},
			"bone16": {
				"rotate": [
					{
						"time": 0,
						"angle": 0,
						"curve": [ 0.235, 0.28, 0.75, 1 ]
					},
					{
						"time": 0.2666,
						"angle": -12.66,
						"curve": [ 0.25, 0, 0.75, 1 ]
					},
					{
						"time": 0.7,
						"angle": 10.94,
						"curve": [ 0.25, 0, 0.804, 0.7 ]
					},
					{ "time": 1, "angle": 0 }
				],
				"translate": [
					{ "time": 0, "x": 0, "y": 0, "curve": "stepped" },
					{ "time": 1, "x": 0, "y": 0 }
				],
				"scale": [
					{ "time": 0, "x": 1, "y": 1, "curve": "stepped" },
					{ "time": 1, "x": 1, "y": 1 }
				]
			},
			"bone20": {
				"rotate": [
					{
						"time": 0,
						"angle": 0,
						"curve": [ 0.187, 0.23, 0.75, 1 ]
					},
					{
						"time": 0.3,
						"angle": 25.13,
						"curve": [ 0.25, 0, 0.75, 1 ]
					},
					{
						"time": 0.7666,
						"angle": -6.33,
						"curve": [ 0.25, 0, 0.798, 0.71 ]
					},
					{ "time": 1, "angle": 0 }
				],
				"translate": [
					{ "time": 0, "x": 0, "y": 0, "curve": "stepped" },
					{ "time": 1, "x": 0, "y": 0 }
				],
				"scale": [
					{ "time": 0, "x": 1, "y": 1, "curve": "stepped" },
					{ "time": 1, "x": 1, "y": 1 }
				]
			},
			"bone5": {
				"rotate": [
					{
						"time": 0,
						"angle": 0,
						"curve": [ 0.25, 0, 0.75, 1 ]
					},
					{
						"time": 0.5,
						"angle": 16.7,
						"curve": [ 0.25, 0, 0.75, 1 ]
					},
					{ "time": 1, "angle": 0 }
				],
				"translate": [
					{ "time": 0, "x": 0, "y": 0, "curve": "stepped" },
					{ "time": 1, "x": 0, "y": 0 }
				],
				"scale": [
					{ "time": 0, "x": 1, "y": 1, "curve": "stepped" },
					{ "time": 1, "x": 1, "y": 1 }
				]
			},
			"bone7": {
				"rotate": [
					{
						"time": 0,
						"angle": 0,
						"curve": [ 0.25, 0, 0.75, 1 ]
					},
					{
						"time": 0.5666,
						"angle": 25.88,
						"curve": [ 0.25, 0, 0.75, 1 ]
					},
					{ "time": 1, "angle": 0 }
				],
				"translate": [
					{ "time": 0, "x": 0, "y": 0, "curve": "stepped" },
					{ "time": 1, "x": 0, "y": 0 }
				],
				"scale": [
					{ "time": 0, "x": 1, "y": 1, "curve": "stepped" },
					{ "time": 1, "x": 1, "y": 1 }
				]
			},
			"bone6": {
				"rotate": [
					{
						"time": 0,
						"angle": 0,
						"curve": [ 0.204, 0.31, 0.75, 1 ]
					},
					{
						"time": 0.3,
						"angle": -21.71,
						"curve": [ 0.25, 0, 0.75, 1 ]
					},
					{
						"time": 0.7333,
						"angle": 11.05,
						"curve": [ 0.25, 0, 0.798, 0.73 ]
					},
					{ "time": 1, "angle": 0 }
				],
				"translate": [
					{ "time": 0, "x": 0, "y": 0, "curve": "stepped" },
					{ "time": 1, "x": 0, "y": 0 }
				],
				"scale": [
					{ "time": 0, "x": 1, "y": 1, "curve": "stepped" },
					{ "time": 1, "x": 1, "y": 1 }
				]
			}
		},
		"ffd": {
			"default": {
				"chibang12": {
					"chibang1": [
						{ "time": 0 }
					]
				},
				"daizi12": {
					"daizi1": [
						{ "time": 0 }
					]
				},
				"daizi22": {
					"daizi2": [
						{ "time": 0 }
					]
				},
				"jiao12": {
					"jiao1": [
						{ "time": 0 }
					]
				},
				"jiao22": {
					"jiao2": [
						{ "time": 0 }
					]
				},
				"shenti2": {
					"shenti": [
						{ "time": 0 }
					]
				},
				"weiba2": {
					"weiba": [
						{ "time": 0 }
					]
				},
				"yumao2": {
					"yumao2": [
						{ "time": 0 }
					]
				},
				"yumao12": {
					"yumao1": [
						{ "time": 0 }
					]
				},
				"yumao32": {
					"yumao3": [
						{ "time": 0 }
					]
				}
			}
		},
		"drawOrder": [
			{ "time": 0 }
		]
	}
}
}